Workbook

Sheet Projects Cashflow
K1: =SUBTOTAL(9,K3:K1048576) -> 1574767 | L1: =SUBTOTAL(9,L3:L1048576) -> 10563367 | M1: =SUBTOTAL(9,M3:M1048576) -> 1.2557259e+09 | N1: =SUBTOTAL(9,N3:N1048576) -> 5.3993238e+08 | O1: =SUBTOTAL(9,O3:O1048576) -> 4.3767954e+08 | P1: =SUBTOTAL(9,P3:P1048576) -> 4.9824083e+08 | Q1: =SUBTOTAL(9,Q3:Q1048576) -> 2.4776673e+08 | R1: =SUBTOTAL(9,R3:R1048576) -> 3.2591407e+08 | ... W1: =SUBTOTAL(9,W3:W1048576) -> 5.08522e+09 | AG1: =SUBTOTAL(9,AG3:AG1048576) -> 7.694308e+09 | AH1: =SUBTOTAL(9,AH3:AH1048576) -> 5.3650702e+09
B2: Com | C2: COST_CENTER | D2: PROJECT2 | E2: PROJECT_NAME | F2: TASK | G2: GL | H2: Future | I2: EXPENDITURE_TYPE | J2: CF_TYPE | K2: 01-2026 | L2: 02-2026 | M2: 03-2026 | N2: 04-2026 | O2: 05-2026 | P2: 06-2026 | Q2: 07-2026 | R2: 08-2026 | S2: 09-2026 | T2: 10-2026 | U2: 11-2026 | V2: 12-2026 | W2: Total | X2: GL_COMBINATION | Y2: SECTOR | Z2: DEPARTMENT | AA2: GL_ACCOUNT | AB2: APPROPRIATION | AC2: CHAPTER | AD2: PROGRAM | AE2: BUSINESS_UNIT | AF2: PROJECT_TYPE | AG2: ANNUAL_BUDGET | AH2: Total V3
B3: =C3&D3&F3&G3&H3 -> 45100114511000015Sponsorship Fees-N1424811200104 | C3: 4510011 | D3: 4511000015 | E3: Ex-SH-MNS | F3: Sponsorship Fees-N1 | G3: 424811 | H3: 200104 | I3: 424811 - Sponsorship expenses/contributions | J3: APPROVED | K3: =_xlfn.XLOOKUP(B3,[1]Sheet1!$B:$B,[1]Sheet1!$N:$N,0) -> 0 | L3: =_xlfn.XLOOKUP(B3,[1]Sheet1!$B:$B,[1]Sheet1!$O:$O,0) -> 0 | M3: =_xlfn.XLOOKUP(B3,[1]Sheet1!$B:$B,[1]Sheet1!$P:$P,0) -> 30000000 | N3: =_xlfn.XLOOKUP(B3,[1]Sheet1!$B:$B,[1]Sheet1!$Q:$Q,0) -> 0 | O3: =_xlfn.XLOOKUP(B3,[1]Sheet1!$B:$B,[1]Sheet1!$R:$R,0) -> 0 | P3: =_xlfn.XLOOKUP(B3,[1]Sheet1!$B:$B,[1]Sheet1!$S:$S,0) -> 0 | Q3: =_xlfn.XLOOKUP(B3,[1]Sheet1!$B:$B,[1]Sheet1!$T:$T,0) -> 0 | R3: =_xlfn.XLOOKUP(B3,[1]Sheet1!$B:$B,[1]Sheet1!$U:$U,0) -> 0 | S3: =_xlfn.XLOOKUP(B3,[1]Sheet1!$B:$B,[1]Sheet1!$V:$V,0) -> 0 | T3: =_xlfn.XLOOKUP(B3,[1]Sheet1!$B:$B,[1]Sheet1!$W:$W,0) -> 0 | U3: =_xlfn.XLOOKUP(B3,[1]Sheet1!$B:$B,[1]Sheet1!$X:$X,0) -> 0 | V3: =_xlfn.XLOOKUP(B3,[1]Sheet1!$B:$B,[1]Sheet1!$Y:$Y,0) -> 0 | W3: =SUM(K3:V3) -> 30000000 | X3: 451.070101.4510011.1.424811.4510000.200104.000.000000.000000 | Y3: Executive Office | Z3: DCT - Executive Affairs Department | AA3: 424811 - Sponsorship expenses/contributions | AB3: 200104 - FA104-Opex Expense | AC3: Chapter 2 | AD3: 070101 - Corporate Office | AE3: Department of Culture and Tourism | AF3: DCT OPEX Project Type | AG3: 30000000 | AH3: =_xlfn.XLOOKUP(B3,[1]Sheet1!$B:$B,[1]Sheet1!$AB:$AB,0) -> 30000000
B4: =C4&D4&F4&G4&H4 -> 45101404511000016Audit Services-N421125200104 | C4: 4510140 | D4: 4511000016 | E4: EX-INR Audit | F4: Audit Services-N | G4: 421125 | H4: 200104 | I4: 421125 - Professional Operational Service expenses | J4: APPROVED | K4: =_xlfn.XLOOKUP(B4,[1]Sheet1!$B:$B,[1]Sheet1!$N:$N,0) -> 0 | L4: =_xlfn.XLOOKUP(B4,[1]Sheet1!$B:$B,[1]Sheet1!$O:$O,0) -> 0 | M4: =_xlfn.XLOOKUP(B4,[1]Sheet1!$B:$B,[1]Sheet1!$P:$P,0) -> 0 | N4: =_xlfn.XLOOKUP(B4,[1]Sheet1!$B:$B,[1]Sheet1!$Q:$Q,0) -> 454200 | O4: =_xlfn.XLOOKUP(B4,[1]Sheet1!$B:$B,[1]Sheet1!$R:$R,0) -> 142800 | P4: =_xlfn.XLOOKUP(B4,[1]Sheet1!$B:$B,[1]Sheet1!$S:$S,0) -> 142800 | Q4: =_xlfn.XLOOKUP(B4,[1]Sheet1!$B:$B,[1]Sheet1!$T:$T,0) -> 142800 | R4: =_xlfn.XLOOKUP(B4,[1]Sheet1!$B:$B,[1]Sheet1!$U:$U,0) -> 142800 | S4: =_xlfn.XLOOKUP(B4,[1]Sheet1!$B:$B,[1]Sheet1!$V:$V,0) -> 464500 | T4: =_xlfn.XLOOKUP(B4,[1]Sheet1!$B:$B,[1]Sheet1!$W:$W,0) -> 342800 | U4: =_xlfn.XLOOKUP(B4,[1]Sheet1!$B:$B,[1]Sheet1!$X:$X,0) -> 802800 | V4: =_xlfn.XLOOKUP(B4,[1]Sheet1!$B:$B,[1]Sheet1!$Y:$Y,0) -> 464500 | W4: =SUM(K4:V4) -> 3100000 | X4: 451.070109.4510140.1.421125.4510000.200104.000.000000.000000 | Y4: Internal Audit | Z4: DCT - Internal Audit Dept | AA4: 421125 - Professional Operational Service expenses | AB4: 200104 - FA104-Opex Expense | AC4: Chapter 2 | AD4: 070109 - Internal Audit and Risk Management | AE4: Department of Culture and Tourism | AF4: DCT OPEX Project Type | AG4: 2669667 | AH4: =_xlfn.XLOOKUP(B4,[1]Sheet1!$B:$B,[1]Sheet1!$AB:$AB,0) -> 2669667
B5: =C5&D5&F5&G5&H5 -> 45101404511000016Freelancers-N424521200104 | C5: 4510140 | D5: 4511000016 | E5: EX-INR Audit | F5: Freelancers-N | G5: 424521 | H5: 200104 | I5: 424521 - Manpower supply "Other Than IT Related" | J5: APPROVED | K5: =_xlfn.XLOOKUP(B5,[1]Sheet1!$B:$B,[1]Sheet1!$N:$N,0) -> 0 | L5: =_xlfn.XLOOKUP(B5,[1]Sheet1!$B:$B,[1]Sheet1!$O:$O,0) -> 0 | M5: =_xlfn.XLOOKUP(B5,[1]Sheet1!$B:$B,[1]Sheet1!$P:$P,0) -> 0 | N5: =_xlfn.XLOOKUP(B5,[1]Sheet1!$B:$B,[1]Sheet1!$Q:$Q,0) -> 0 | O5: =_xlfn.XLOOKUP(B5,[1]Sheet1!$B:$B,[1]Sheet1!$R:$R,0) -> 0 | P5: =_xlfn.XLOOKUP(B5,[1]Sheet1!$B:$B,[1]Sheet1!$S:$S,0) -> 0 | Q5: =_xlfn.XLOOKUP(B5,[1]Sheet1!$B:$B,[1]Sheet1!$T:$T,0) -> 0 | R5: =_xlfn.XLOOKUP(B5,[1]Sheet1!$B:$B,[1]Sheet1!$U:$U,0) -> 0 | S5: =_xlfn.XLOOKUP(B5,[1]Sheet1!$B:$B,[1]Sheet1!$V:$V,0) -> 0 | T5: =_xlfn.XLOOKUP(B5,[1]Sheet1!$B:$B,[1]Sheet1!$W:$W,0) -> 0 | U5: =_xlfn.XLOOKUP(B5,[1]Sheet1!$B:$B,[1]Sheet1!$X:$X,0) -> 0 | V5: =_xlfn.XLOOKUP(B5,[1]Sheet1!$B:$B,[1]Sheet1!$Y:$Y,0) -> 0 | W5: =SUM(K5:V5) -> 0 | X5: 451.070109.4510140.1.424521.4510000.200104.000.000000.000000 | Y5: Internal Audit | Z5: DCT - Internal Audit Dept | AA5: 424521 - Manpower supply Other Than IT Related | AB5: 200104 - FA104-Opex Expense | AC5: Chapter 2 | AD5: 070109 - Internal Audit and Risk Management | AE5: Department of Culture and Tourism | AF5: DCT OPEX Project Type | AG5: 430333 | AH5: =_xlfn.XLOOKUP(B5,[1]Sheet1!$B:$B,[1]Sheet1!$AB:$AB,0) -> 430333
B6: =C6&D6&F6&G6&H6 -> 45101404511000016Mission & Travel-N423821200104 | C6: 4510140 | D6: 4511000016 | E6: EX-INR Audit | F6: Mission & Travel-N | G6: 423821 | H6: 200104 | I6: 423821 - Business Travel - Per Diem Allowances | J6: APPROVED | K6: =_xlfn.XLOOKUP(B6,[1]Sheet1!$B:$B,[1]Sheet1!$N:$N,0) -> 0 | L6: =_xlfn.XLOOKUP(B6,[1]Sheet1!$B:$B,[1]Sheet1!$O:$O,0) -> 0 | M6: =_xlfn.XLOOKUP(B6,[1]Sheet1!$B:$B,[1]Sheet1!$P:$P,0) -> 0 | N6: =_xlfn.XLOOKUP(B6,[1]Sheet1!$B:$B,[1]Sheet1!$Q:$Q,0) -> 0 | O6: =_xlfn.XLOOKUP(B6,[1]Sheet1!$B:$B,[1]Sheet1!$R:$R,0) -> 0 | P6: =_xlfn.XLOOKUP(B6,[1]Sheet1!$B:$B,[1]Sheet1!$S:$S,0) -> 0 | Q6: =_xlfn.XLOOKUP(B6,[1]Sheet1!$B:$B,[1]Sheet1!$T:$T,0) -> 0 | R6: =_xlfn.XLOOKUP(B6,[1]Sheet1!$B:$B,[1]Sheet1!$U:$U,0) -> 0 | S6: =_xlfn.XLOOKUP(B6,[1]Sheet1!$B:$B,[1]Sheet1!$V:$V,0) -> 0 | T6: =_xlfn.XLOOKUP(B6,[1]Sheet1!$B:$B,[1]Sheet1!$W:$W,0) -> 0 | U6: =_xlfn.XLOOKUP(B6,[1]Sheet1!$B:$B,[1]Sheet1!$X:$X,0) -> 125000 | V6: =_xlfn.XLOOKUP(B6,[1]Sheet1!$B:$B,[1]Sheet1!$Y:$Y,0) -> 0 | W6: =SUM(K6:V6) -> 125000 | X6: 451.070109.4510140.1.423821.4510000.200104.000.000000.000000 | Y6: Internal Audit | Z6: DCT - Internal Audit Dept | AA6: 423821 - Business Travel - Per Diem Allowances | AB6: 200104 - FA104-Opex Expense | AC6: Chapter 2 | AD6: 070109 - Internal Audit and Risk Management | AE6: Department of Culture and Tourism | AF6: DCT OPEX Project Type | AG6: 125000 | AH6: =_xlfn.XLOOKUP(B6,[1]Sheet1!$B:$B,[1]Sheet1!$AB:$AB,0) -> 125000
B7: =C7&D7&F7&G7&H7 -> 45101404511000016Other Expenses-N424991200104 | C7: 4510140 | D7: 4511000016 | E7: EX-INR Audit | F7: Other Expenses-N | G7: 424991 | H7: 200104 | I7: 424991 - Other services, not specifically mentioned elsewhere | J7: APPROVED | K7: =_xlfn.XLOOKUP(B7,[1]Sheet1!$B:$B,[1]Sheet1!$N:$N,0) -> 0 | L7: =_xlfn.XLOOKUP(B7,[1]Sheet1!$B:$B,[1]Sheet1!$O:$O,0) -> 0 | M7: =_xlfn.XLOOKUP(B7,[1]Sheet1!$B:$B,[1]Sheet1!$P:$P,0) -> 2926.04 | N7: =_xlfn.XLOOKUP(B7,[1]Sheet1!$B:$B,[1]Sheet1!$Q:$Q,0) -> 0 | O7: =_xlfn.XLOOKUP(B7,[1]Sheet1!$B:$B,[1]Sheet1!$R:$R,0) -> 0 | P7: =_xlfn.XLOOKUP(B7,[1]Sheet1!$B:$B,[1]Sheet1!$S:$S,0) -> 0 | Q7: =_xlfn.XLOOKUP(B7,[1]Sheet1!$B:$B,[1]Sheet1!$T:$T,0) -> 0 | R7: =_xlfn.XLOOKUP(B7,[1]Sheet1!$B:$B,[1]Sheet1!$U:$U,0) -> 0 | S7: =_xlfn.XLOOKUP(B7,[1]Sheet1!$B:$B,[1]Sheet1!$V:$V,0) -> 59574 | T7: =_xlfn.XLOOKUP(B7,[1]Sheet1!$B:$B,[1]Sheet1!$W:$W,0) -> 0 | U7: =_xlfn.XLOOKUP(B7,[1]Sheet1!$B:$B,[1]Sheet1!$X:$X,0) -> 62500 | V7: =_xlfn.XLOOKUP(B7,[1]Sheet1!$B:$B,[1]Sheet1!$Y:$Y,0) -> 0 | W7: =SUM(K7:V7) -> 125000.04 | X7: 451.070109.4510140.1.424991.4510000.200104.000.000000.000000 | Y7: Internal Audit | Z7: DCT - Internal Audit Dept | AA7: 424991 - Other services, not specifically mentioned elsewhere | AB7: 200104 - FA104-Opex Expense | AC7: Chapter 2 | AD7: 070109 - Internal Audit and Risk Management | AE7: Department of Culture and Tourism | AF7: DCT OPEX Project Type | AG7: 125000 | AH7: =_xlfn.XLOOKUP(B7,[1]Sheet1!$B:$B,[1]Sheet1!$AB:$AB,0) -> 125000.04
B8: =C8&D8&F8&G8&H8 -> 45112504511000019Activation&Prog-N422401200104 | C8: 4511250 | D8: 4511000019 | E8: CS-Art Comm-Qatara | F8: Activation&Prog-N | G8: 422401 | H8: 200104 | I8: 422401 - Conferences, seminars, exhib ,events: -deactivate | J8: APPROVED | K8: =_xlfn.XLOOKUP(B8,[1]Sheet1!$B:$B,[1]Sheet1!$N:$N,0) -> 0 | L8: =_xlfn.XLOOKUP(B8,[1]Sheet1!$B:$B,[1]Sheet1!$O:$O,0) -> 0 | M8: =_xlfn.XLOOKUP(B8,[1]Sheet1!$B:$B,[1]Sheet1!$P:$P,0) -> 562600 | N8: =_xlfn.XLOOKUP(B8,[1]Sheet1!$B:$B,[1]Sheet1!$Q:$Q,0) -> 0 | O8: =_xlfn.XLOOKUP(B8,[1]Sheet1!$B:$B,[1]Sheet1!$R:$R,0) -> 0 | P8: =_xlfn.XLOOKUP(B8,[1]Sheet1!$B:$B,[1]Sheet1!$S:$S,0) -> 0 | Q8: =_xlfn.XLOOKUP(B8,[1]Sheet1!$B:$B,[1]Sheet1!$T:$T,0) -> 0 | R8: =_xlfn.XLOOKUP(B8,[1]Sheet1!$B:$B,[1]Sheet1!$U:$U,0) -> 0 | S8: =_xlfn.XLOOKUP(B8,[1]Sheet1!$B:$B,[1]Sheet1!$V:$V,0) -> 0 | T8: =_xlfn.XLOOKUP(B8,[1]Sheet1!$B:$B,[1]Sheet1!$W:$W,0) -> 0 | U8: =_xlfn.XLOOKUP(B8,[1]Sheet1!$B:$B,[1]Sheet1!$X:$X,0) -> 0 | V8: =_xlfn.XLOOKUP(B8,[1]Sheet1!$B:$B,[1]Sheet1!$Y:$Y,0) -> 430400 | W8: =SUM(K8:V8) -> 993000 | X8: 451.070205.4511250.1.422401.4510000.200104.000.000000.000000 | Y8: Culture | Z8: DCT - Culture Sites Management Department | AA8: 422401 - Conferences, seminars and exhibitions and other events: -deactivate | AB8: 200104 - FA104-Opex Expense | AC8: Chapter 2 | AD8: 070205 - Cultural site management | AE8: Department of Culture and Tourism | AF8: DCT OPEX Project Type | AG8: 993000 | AH8: =_xlfn.XLOOKUP(B8,[1]Sheet1!$B:$B,[1]Sheet1!$AB:$AB,0) -> 993000
B9: =C9&D9&F9&G9&H9 -> 45112504511000019Ad-hoc Repairs-N426427200104 | C9: 4511250 | D9: 4511000019 | E9: CS-Art Comm-Qatara | F9: Ad-hoc Repairs-N | G9: 426427 | H9: 200104 | I9: 426427 - Maintenance & repair-Exhibition Stands, etc | J9: APPROVED | K9: =_xlfn.XLOOKUP(B9,[1]Sheet1!$B:$B,[1]Sheet1!$N:$N,0) -> 0 | L9: =_xlfn.XLOOKUP(B9,[1]Sheet1!$B:$B,[1]Sheet1!$O:$O,0) -> 0 | M9: =_xlfn.XLOOKUP(B9,[1]Sheet1!$B:$B,[1]Sheet1!$P:$P,0) -> 0 | N9: =_xlfn.XLOOKUP(B9,[1]Sheet1!$B:$B,[1]Sheet1!$Q:$Q,0) -> 30000 | O9: =_xlfn.XLOOKUP(B9,[1]Sheet1!$B:$B,[1]Sheet1!$R:$R,0) -> 30000 | P9: =_xlfn.XLOOKUP(B9,[1]Sheet1!$B:$B,[1]Sheet1!$S:$S,0) -> 30000 | Q9: =_xlfn.XLOOKUP(B9,[1]Sheet1!$B:$B,[1]Sheet1!$T:$T,0) -> 30000 | R9: =_xlfn.XLOOKUP(B9,[1]Sheet1!$B:$B,[1]Sheet1!$U:$U,0) -> 5316 | S9: =_xlfn.XLOOKUP(B9,[1]Sheet1!$B:$B,[1]Sheet1!$V:$V,0) -> 17658 | T9: =_xlfn.XLOOKUP(B9,[1]Sheet1!$B:$B,[1]Sheet1!$W:$W,0) -> 19368 | U9: =_xlfn.XLOOKUP(B9,[1]Sheet1!$B:$B,[1]Sheet1!$X:$X,0) -> 0 | V9: =_xlfn.XLOOKUP(B9,[1]Sheet1!$B:$B,[1]Sheet1!$Y:$Y,0) -> 0 | W9: =SUM(K9:V9) -> 162342 | X9: 451.070205.4511250.1.426427.4510000.200104.000.000000.000000 | Y9: Culture | Z9: DCT - Culture Sites Management Department | AA9: 426427 - Maintenance & repair-Exhibition Stands, etc | AB9: 200104 - FA104-Opex Expense | AC9: Chapter 2 | AD9: 070205 - Cultural site management | AE9: Department of Culture and Tourism | AF9: DCT OPEX Project Type | AG9: 162342 | AH9: =_xlfn.XLOOKUP(B9,[1]Sheet1!$B:$B,[1]Sheet1!$AB:$AB,0) -> 162342
B10: =C10&D10&F10&G10&H10 -> 45112504511000019Admin Expenses-N1421125200104 | C10: 4511250 | D10: 4511000019 | E10: CS-Art Comm-Qatara | F10: Admin Expenses-N1 | G10: 421125 | H10: 200104 | I10: 421125 - Professional Operational Service expenses | J10: APPROVED | K10: =_xlfn.XLOOKUP(B10,[1]Sheet1!$B:$B,[1]Sheet1!$N:$N,0) -> 0 | L10: =_xlfn.XLOOKUP(B10,[1]Sheet1!$B:$B,[1]Sheet1!$O:$O,0) -> 0 | M10: =_xlfn.XLOOKUP(B10,[1]Sheet1!$B:$B,[1]Sheet1!$P:$P,0) -> 0 | N10: =_xlfn.XLOOKUP(B10,[1]Sheet1!$B:$B,[1]Sheet1!$Q:$Q,0) -> 0 | O10: =_xlfn.XLOOKUP(B10,[1]Sheet1!$B:$B,[1]Sheet1!$R:$R,0) -> 40000 | P10: =_xlfn.XLOOKUP(B10,[1]Sheet1!$B:$B,[1]Sheet1!$S:$S,0) -> 40000 | Q10: =_xlfn.XLOOKUP(B10,[1]Sheet1!$B:$B,[1]Sheet1!$T:$T,0) -> 40000 | R10: =_xlfn.XLOOKUP(B10,[1]Sheet1!$B:$B,[1]Sheet1!$U:$U,0) -> 40000 | S10: =_xlfn.XLOOKUP(B10,[1]Sheet1!$B:$B,[1]Sheet1!$V:$V,0) -> 40000 | T10: =_xlfn.XLOOKUP(B10,[1]Sheet1!$B:$B,[1]Sheet1!$W:$W,0) -> 71800 | U10: =_xlfn.XLOOKUP(B10,[1]Sheet1!$B:$B,[1]Sheet1!$X:$X,0) -> 0 | V10: =_xlfn.XLOOKUP(B10,[1]Sheet1!$B:$B,[1]Sheet1!$Y:$Y,0) -> 0 | W10: =SUM(K10:V10) -> 271800 | X10: 451.070205.4511250.1.421125.4510000.200104.000.000000.000000 | Y10: Culture | Z10: DCT - Culture Sites Management Department | AA10: 421125 - Professional Operational Service expenses | AB10: 200104 - FA104-Opex Expense | AC10: Chapter 2 | AD10: 070205 - Cultural site management | AE10: Department of Culture and Tourism | AF10: DCT OPEX Project Type | AG10: 271800 | AH10: =_xlfn.XLOOKUP(B10,[1]Sheet1!$B:$B,[1]Sheet1!$AB:$AB,0) -> 271800
B11: =C11&D11&F11&G11&H11 -> 45112504511000019Art Materials-N1432626200104 | C11: 4511250 | D11: 4511000019 | E11: CS-Art Comm-Qatara | F11: Art Materials-N1 | G11: 432626 | H11: 200104 | I11: 432626 - Music Band related items | J11: APPROVED | K11: =_xlfn.XLOOKUP(B11,[1]Sheet1!$B:$B,[1]Sheet1!$N:$N,0) -> 0 | L11: =_xlfn.XLOOKUP(B11,[1]Sheet1!$B:$B,[1]Sheet1!$O:$O,0) -> 0 | M11: =_xlfn.XLOOKUP(B11,[1]Sheet1!$B:$B,[1]Sheet1!$P:$P,0) -> 0 | N11: =_xlfn.XLOOKUP(B11,[1]Sheet1!$B:$B,[1]Sheet1!$Q:$Q,0) -> 75000 | O11: =_xlfn.XLOOKUP(B11,[1]Sheet1!$B:$B,[1]Sheet1!$R:$R,0) -> 0 | P11: =_xlfn.XLOOKUP(B11,[1]Sheet1!$B:$B,[1]Sheet1!$S:$S,0) -> 50000 | Q11: =_xlfn.XLOOKUP(B11,[1]Sheet1!$B:$B,[1]Sheet1!$T:$T,0) -> 0 | R11: =_xlfn.XLOOKUP(B11,[1]Sheet1!$B:$B,[1]Sheet1!$U:$U,0) -> 0 | S11: =_xlfn.XLOOKUP(B11,[1]Sheet1!$B:$B,[1]Sheet1!$V:$V,0) -> 0 | T11: =_xlfn.XLOOKUP(B11,[1]Sheet1!$B:$B,[1]Sheet1!$W:$W,0) -> 25000 | U11: =_xlfn.XLOOKUP(B11,[1]Sheet1!$B:$B,[1]Sheet1!$X:$X,0) -> 0 | V11: =_xlfn.XLOOKUP(B11,[1]Sheet1!$B:$B,[1]Sheet1!$Y:$Y,0) -> 0 | W11: =SUM(K11:V11) -> 150000 | X11: 451.070205.4511250.1.432626.4510000.200104.000.000000.000000 | Y11: Culture | Z11: DCT - Culture Sites Management Department | AA11: 432626 - Music Band related items | AB11: 200104 - FA104-Opex Expense | AC11: Chapter 2 | AD11: 070205 - Cultural site management | AE11: Department of Culture and Tourism | AF11: DCT OPEX Project Type | AG11: 150000 | AH11: =_xlfn.XLOOKUP(B11,[1]Sheet1!$B:$B,[1]Sheet1!$AB:$AB,0) -> 150000
B12: =C12&D12&F12&G12&H12 -> 45112504511000019Cleaning Service-N422311200104 | C12: 4511250 | D12: 4511000019 | E12: CS-Art Comm-Qatara | F12: Cleaning Service-N | G12: 422311 | H12: 200104 | I12: 422311 - Cleaning Services: Business premises | J12: APPROVED | K12: =_xlfn.XLOOKUP(B12,[1]Sheet1!$B:$B,[1]Sheet1!$N:$N,0) -> 0 | L12: =_xlfn.XLOOKUP(B12,[1]Sheet1!$B:$B,[1]Sheet1!$O:$O,0) -> 0 | M12: =_xlfn.XLOOKUP(B12,[1]Sheet1!$B:$B,[1]Sheet1!$P:$P,0) -> 0 | N12: =_xlfn.XLOOKUP(B12,[1]Sheet1!$B:$B,[1]Sheet1!$Q:$Q,0) -> 45000 | O12: =_xlfn.XLOOKUP(B12,[1]Sheet1!$B:$B,[1]Sheet1!$R:$R,0) -> 15000 | P12: =_xlfn.XLOOKUP(B12,[1]Sheet1!$B:$B,[1]Sheet1!$S:$S,0) -> 15000 | Q12: =_xlfn.XLOOKUP(B12,[1]Sheet1!$B:$B,[1]Sheet1!$T:$T,0) -> 15000 | R12: =_xlfn.XLOOKUP(B12,[1]Sheet1!$B:$B,[1]Sheet1!$U:$U,0) -> 15000 | S12: =_xlfn.XLOOKUP(B12,[1]Sheet1!$B:$B,[1]Sheet1!$V:$V,0) -> 15000 | T12: =_xlfn.XLOOKUP(B12,[1]Sheet1!$B:$B,[1]Sheet1!$W:$W,0) -> 30000 | U12: =_xlfn.XLOOKUP(B12,[1]Sheet1!$B:$B,[1]Sheet1!$X:$X,0) -> 30000 | V12: =_xlfn.XLOOKUP(B12,[1]Sheet1!$B:$B,[1]Sheet1!$Y:$Y,0) -> 38430 | W12: =SUM(K12:V12) -> 218430 | X12: 451.070205.4511250.1.422311.4510000.200104.000.000000.000000 | Y12: Culture | Z12: DCT - Culture Sites Management Department | AA12: 422311 - Cleaning Services: Business premises | AB12: 200104 - FA104-Opex Expense | AC12: Chapter 2 | AD12: 070205 - Cultural site management | AE12: Department of Culture and Tourism | AF12: DCT OPEX Project Type | AG12: 218430 | AH12: =_xlfn.XLOOKUP(B12,[1]Sheet1!$B:$B,[1]Sheet1!$AB:$AB,0) -> 218430
B13: =C13&D13&F13&G13&H13 -> 45112504511000019Freelancers-N424521200104 | C13: 4511250 | D13: 4511000019 | E13: CS-Art Comm-Qatara | F13: Freelancers-N | G13: 424521 | H13: 200104 | I13: 424521 - Manpower supply "Other Than IT Related" | J13: APPROVED | K13: =_xlfn.XLOOKUP(B13,[1]Sheet1!$B:$B,[1]Sheet1!$N:$N,0) -> 0 | L13: =_xlfn.XLOOKUP(B13,[1]Sheet1!$B:$B,[1]Sheet1!$O:$O,0) -> 0 | M13: =_xlfn.XLOOKUP(B13,[1]Sheet1!$B:$B,[1]Sheet1!$P:$P,0) -> 223600 | N13: =_xlfn.XLOOKUP(B13,[1]Sheet1!$B:$B,[1]Sheet1!$Q:$Q,0) -> 71600 | O13: =_xlfn.XLOOKUP(B13,[1]Sheet1!$B:$B,[1]Sheet1!$R:$R,0) -> 98400 | P13: =_xlfn.XLOOKUP(B13,[1]Sheet1!$B:$B,[1]Sheet1!$S:$S,0) -> 98400 | Q13: =_xlfn.XLOOKUP(B13,[1]Sheet1!$B:$B,[1]Sheet1!$T:$T,0) -> 98400 | R13: =_xlfn.XLOOKUP(B13,[1]Sheet1!$B:$B,[1]Sheet1!$U:$U,0) -> 98400 | S13: =_xlfn.XLOOKUP(B13,[1]Sheet1!$B:$B,[1]Sheet1!$V:$V,0) -> 98400 | T13: =_xlfn.XLOOKUP(B13,[1]Sheet1!$B:$B,[1]Sheet1!$W:$W,0) -> 150400 | U13: =_xlfn.XLOOKUP(B13,[1]Sheet1!$B:$B,[1]Sheet1!$X:$X,0) -> 150400 | V13: =_xlfn.XLOOKUP(B13,[1]Sheet1!$B:$B,[1]Sheet1!$Y:$Y,0) -> 150400 | W13: =SUM(K13:V13) -> 1238400 | X13: 451.070205.4511250.1.424521.4510000.200104.000.000000.000000 | Y13: Culture | Z13: DCT - Culture Sites Management Department | AA13: 424521 - Manpower supply Other Than IT Related | AB13: 200104 - FA104-Opex Expense | AC13: Chapter 2 | AD13: 070205 - Cultural site management | AE13: Department of Culture and Tourism | AF13: DCT OPEX Project Type | AG13: 1238400 | AH13: =_xlfn.XLOOKUP(B13,[1]Sheet1!$B:$B,[1]Sheet1!$AB:$AB,0) -> 1238400
B14: =C14&D14&F14&G14&H14 -> 45112504511000019Hospitality-N424761200104 | C14: 4511250 | D14: 4511000019 | E14: CS-Art Comm-Qatara | F14: Hospitality-N | G14: 424761 | H14: 200104 | I14: 424761 - Entertainment and hospitality | J14: APPROVED | K14: =_xlfn.XLOOKUP(B14,[1]Sheet1!$B:$B,[1]Sheet1!$N:$N,0) -> 0 | L14: =_xlfn.XLOOKUP(B14,[1]Sheet1!$B:$B,[1]Sheet1!$O:$O,0) -> 0 | M14: =_xlfn.XLOOKUP(B14,[1]Sheet1!$B:$B,[1]Sheet1!$P:$P,0) -> 0 | N14: =_xlfn.XLOOKUP(B14,[1]Sheet1!$B:$B,[1]Sheet1!$Q:$Q,0) -> 60000 | O14: =_xlfn.XLOOKUP(B14,[1]Sheet1!$B:$B,[1]Sheet1!$R:$R,0) -> 30000 | P14: =_xlfn.XLOOKUP(B14,[1]Sheet1!$B:$B,[1]Sheet1!$S:$S,0) -> 30000 | Q14: =_xlfn.XLOOKUP(B14,[1]Sheet1!$B:$B,[1]Sheet1!$T:$T,0) -> 30000 | R14: =_xlfn.XLOOKUP(B14,[1]Sheet1!$B:$B,[1]Sheet1!$U:$U,0) -> 30000 | S14: =_xlfn.XLOOKUP(B14,[1]Sheet1!$B:$B,[1]Sheet1!$V:$V,0) -> 30000 | T14: =_xlfn.XLOOKUP(B14,[1]Sheet1!$B:$B,[1]Sheet1!$W:$W,0) -> 30000 | U14: =_xlfn.XLOOKUP(B14,[1]Sheet1!$B:$B,[1]Sheet1!$X:$X,0) -> 25000 | V14: =_xlfn.XLOOKUP(B14,[1]Sheet1!$B:$B,[1]Sheet1!$Y:$Y,0) -> 0 | W14: =SUM(K14:V14) -> 265000 | X14: 451.070205.4511250.1.424761.4510000.200104.000.000000.000000 | Y14: Culture | Z14: DCT - Culture Sites Management Department | AA14: 424761 - Entertainment and hospitality | AB14: 200104 - FA104-Opex Expense | AC14: Chapter 2 | AD14: 070205 - Cultural site management | AE14: Department of Culture and Tourism | AF14: DCT OPEX Project Type | AG14: 265000 | AH14: =_xlfn.XLOOKUP(B14,[1]Sheet1!$B:$B,[1]Sheet1!$AB:$AB,0) -> 265000
... B1383: =C1383&D1383&F1383&G1383&H1383 -> 45151004511001730Trade Partners-IO461412402066 | C1383: 4515100 | D1383: 4511001730 | E1383: Kompass TO/TA - HBO | F1383: Trade Partners-IO | G1383: 461412 | H1383: 402066 | I1383: 461412 - Support to AD tourism development program | J1383: APPROVED | K1383: =_xlfn.XLOOKUP(B1383,[1]Sheet1!$B:$B,[1]Sheet1!$N:$N,0) -> 0 | L1383: =_xlfn.XLOOKUP(B1383,[1]Sheet1!$B:$B,[1]Sheet1!$O:$O,0) -> 0 | M1383: =_xlfn.XLOOKUP(B1383,[1]Sheet1!$B:$B,[1]Sheet1!$P:$P,0) -> 0 | N1383: =_xlfn.XLOOKUP(B1383,[1]Sheet1!$B:$B,[1]Sheet1!$Q:$Q,0) -> 0 | O1383: =_xlfn.XLOOKUP(B1383,[1]Sheet1!$B:$B,[1]Sheet1!$R:$R,0) -> 0 | P1383: =_xlfn.XLOOKUP(B1383,[1]Sheet1!$B:$B,[1]Sheet1!$S:$S,0) -> 0 | Q1383: =_xlfn.XLOOKUP(B1383,[1]Sheet1!$B:$B,[1]Sheet1!$T:$T,0) -> 0 | R1383: =_xlfn.XLOOKUP(B1383,[1]Sheet1!$B:$B,[1]Sheet1!$U:$U,0) -> 0 | S1383: =_xlfn.XLOOKUP(B1383,[1]Sheet1!$B:$B,[1]Sheet1!$V:$V,0) -> 0 | T1383: =_xlfn.XLOOKUP(B1383,[1]Sheet1!$B:$B,[1]Sheet1!$W:$W,0) -> 0 | U1383: =_xlfn.XLOOKUP(B1383,[1]Sheet1!$B:$B,[1]Sheet1!$X:$X,0) -> 0 | V1383: =_xlfn.XLOOKUP(B1383,[1]Sheet1!$B:$B,[1]Sheet1!$Y:$Y,0) -> 0 | W1383: =SUM(K1383:V1383) -> 0 | X1383: 451.070503.4515100.1.461412.4510000.402066.000.000000.000000 | Y1383: Tourism | Z1383: DCT-International Operations Department | AA1383: 461412 - Support to AD tourism development program | AB1383: 402066 - FA2066:Tourism Development Program | AC1383: Chapter 4 | AD1383: 070503 - Enhance Visitor Experience | AE1383: Department of Culture and Tourism | AF1383: DCT OPEX Project Type | AG1383: 2098650 | AH1383: =_xlfn.XLOOKUP(B1383,[1]Sheet1!$B:$B,[1]Sheet1!$AB:$AB,0) -> 0
B1384: =C1384&D1384&F1384&G1384&H1384 -> 45102104514000019FZ fees251413000000 | C1384: 4510210 | D1384: 4514000019 | E1384: Free Zone Fees | F1384: FZ fees | G1384: 251413 | H1384: 000000 | I1384: 251413 - Payable to AD GLbl Mrkt | J1384: APPROVED | K1384: =_xlfn.XLOOKUP(B1384,[1]Sheet1!$B:$B,[1]Sheet1!$N:$N,0) -> 0 | L1384: =_xlfn.XLOOKUP(B1384,[1]Sheet1!$B:$B,[1]Sheet1!$O:$O,0) -> 0 | M1384: =_xlfn.XLOOKUP(B1384,[1]Sheet1!$B:$B,[1]Sheet1!$P:$P,0) -> 0 | N1384: =_xlfn.XLOOKUP(B1384,[1]Sheet1!$B:$B,[1]Sheet1!$Q:$Q,0) -> 0 | O1384: =_xlfn.XLOOKUP(B1384,[1]Sheet1!$B:$B,[1]Sheet1!$R:$R,0) -> 0 | P1384: =_xlfn.XLOOKUP(B1384,[1]Sheet1!$B:$B,[1]Sheet1!$S:$S,0) -> 0 | Q1384: =_xlfn.XLOOKUP(B1384,[1]Sheet1!$B:$B,[1]Sheet1!$T:$T,0) -> 0 | R1384: =_xlfn.XLOOKUP(B1384,[1]Sheet1!$B:$B,[1]Sheet1!$U:$U,0) -> 0 | S1384: =_xlfn.XLOOKUP(B1384,[1]Sheet1!$B:$B,[1]Sheet1!$V:$V,0) -> 0 | T1384: =_xlfn.XLOOKUP(B1384,[1]Sheet1!$B:$B,[1]Sheet1!$W:$W,0) -> 0 | U1384: =_xlfn.XLOOKUP(B1384,[1]Sheet1!$B:$B,[1]Sheet1!$X:$X,0) -> 0 | V1384: =_xlfn.XLOOKUP(B1384,[1]Sheet1!$B:$B,[1]Sheet1!$Y:$Y,0) -> 0 | W1384: =SUM(K1384:V1384) -> 0 | X1384: 451.000000.4510210.1.251413.4510000.000000.000.000000.000000 | Y1384: Support Service | Z1384: DCT - Finance Dept | AA1384: 251413 - Long-term Payable to Abu Dhabi Global Market | AB1384: 000000 - Un Specified | AD1384: 000000 - Unspecified | AE1384: Department of Culture and Tourism | AF1384: DCT Trust Project Type | AG1384: 284390.86 | AH1384: =_xlfn.XLOOKUP(B1384,[1]Sheet1!$B:$B,[1]Sheet1!$AB:$AB,0) -> 0
B1385: =C1385&D1385&F1385&G1385&H1385 -> 45110104514000067Admin221390000000 | C1385: 4511010 | D1385: 4514000067 | E1385: DCT Culture Program | F1385: Admin | G1385: 221390 | H1385: 000000 | I1385: 221390 - Other accrued expenses not mentioned elsewhere | J1385: APPROVED | K1385: =_xlfn.XLOOKUP(B1385,[1]Sheet1!$B:$B,[1]Sheet1!$N:$N,0) -> 0 | L1385: =_xlfn.XLOOKUP(B1385,[1]Sheet1!$B:$B,[1]Sheet1!$O:$O,0) -> 0 | M1385: =_xlfn.XLOOKUP(B1385,[1]Sheet1!$B:$B,[1]Sheet1!$P:$P,0) -> 0 | N1385: =_xlfn.XLOOKUP(B1385,[1]Sheet1!$B:$B,[1]Sheet1!$Q:$Q,0) -> 0 | O1385: =_xlfn.XLOOKUP(B1385,[1]Sheet1!$B:$B,[1]Sheet1!$R:$R,0) -> 0 | P1385: =_xlfn.XLOOKUP(B1385,[1]Sheet1!$B:$B,[1]Sheet1!$S:$S,0) -> 0 | Q1385: =_xlfn.XLOOKUP(B1385,[1]Sheet1!$B:$B,[1]Sheet1!$T:$T,0) -> 0 | R1385: =_xlfn.XLOOKUP(B1385,[1]Sheet1!$B:$B,[1]Sheet1!$U:$U,0) -> 0 | S1385: =_xlfn.XLOOKUP(B1385,[1]Sheet1!$B:$B,[1]Sheet1!$V:$V,0) -> 0 | T1385: =_xlfn.XLOOKUP(B1385,[1]Sheet1!$B:$B,[1]Sheet1!$W:$W,0) -> 0 | U1385: =_xlfn.XLOOKUP(B1385,[1]Sheet1!$B:$B,[1]Sheet1!$X:$X,0) -> 0 | V1385: =_xlfn.XLOOKUP(B1385,[1]Sheet1!$B:$B,[1]Sheet1!$Y:$Y,0) -> 0 | W1385: =SUM(K1385:V1385) -> 0 | X1385: 451.000000.4511010.1.221390.4510000.000000.000.000000.000000 | Y1385: Culture | Z1385: DCT - Culture (Central) Dept | AA1385: 221390 - Other accrued expenses not mentioned elsewhere | AB1385: 000000 - Un Specified | AD1385: 000000 - Unspecified | AE1385: Department of Culture and Tourism | AF1385: DCT Trust Project Type | AG1385: 458572.34 | AH1385: =_xlfn.XLOOKUP(B1385,[1]Sheet1!$B:$B,[1]Sheet1!$AB:$AB,0) -> 0
B1386: =C1386&D1386&F1386&G1386&H1386 -> 45110104514000074Event221390000000 | C1386: 4511010 | D1386: 4514000074 | E1386: Mubadala Partnership | F1386: Event | G1386: 221390 | H1386: 000000 | I1386: 221390 - Other accrued expenses not mentioned elsewhere | J1386: APPROVED | K1386: =_xlfn.XLOOKUP(B1386,[1]Sheet1!$B:$B,[1]Sheet1!$N:$N,0) -> 0 | L1386: =_xlfn.XLOOKUP(B1386,[1]Sheet1!$B:$B,[1]Sheet1!$O:$O,0) -> 0 | M1386: =_xlfn.XLOOKUP(B1386,[1]Sheet1!$B:$B,[1]Sheet1!$P:$P,0) -> 0 | N1386: =_xlfn.XLOOKUP(B1386,[1]Sheet1!$B:$B,[1]Sheet1!$Q:$Q,0) -> 0 | O1386: =_xlfn.XLOOKUP(B1386,[1]Sheet1!$B:$B,[1]Sheet1!$R:$R,0) -> 0 | P1386: =_xlfn.XLOOKUP(B1386,[1]Sheet1!$B:$B,[1]Sheet1!$S:$S,0) -> 0 | Q1386: =_xlfn.XLOOKUP(B1386,[1]Sheet1!$B:$B,[1]Sheet1!$T:$T,0) -> 0 | R1386: =_xlfn.XLOOKUP(B1386,[1]Sheet1!$B:$B,[1]Sheet1!$U:$U,0) -> 0 | S1386: =_xlfn.XLOOKUP(B1386,[1]Sheet1!$B:$B,[1]Sheet1!$V:$V,0) -> 0 | T1386: =_xlfn.XLOOKUP(B1386,[1]Sheet1!$B:$B,[1]Sheet1!$W:$W,0) -> 0 | U1386: =_xlfn.XLOOKUP(B1386,[1]Sheet1!$B:$B,[1]Sheet1!$X:$X,0) -> 0 | V1386: =_xlfn.XLOOKUP(B1386,[1]Sheet1!$B:$B,[1]Sheet1!$Y:$Y,0) -> 0 | W1386: =SUM(K1386:V1386) -> 0 | X1386: 451.000000.4511010.1.221390.4510000.000000.000.000000.000000 | Y1386: Culture | Z1386: DCT - Culture (Central) Dept | AA1386: 221390 - Other accrued expenses not mentioned elsewhere | AB1386: 000000 - Un Specified | AD1386: 000000 - Unspecified | AE1386: Department of Culture and Tourism | AF1386: DCT Trust Project Type | AG1386: 326356.58 | AH1386: =_xlfn.XLOOKUP(B1386,[1]Sheet1!$B:$B,[1]Sheet1!$AB:$AB,0) -> 0
B1387: =C1387&D1387&F1387&G1387&H1387 -> 45110104514000074Manpower221390000000 | C1387: 4511010 | D1387: 4514000074 | E1387: Mubadala Partnership | F1387: Manpower | G1387: 221390 | H1387: 000000 | I1387: 221390 - Other accrued expenses not mentioned elsewhere | J1387: APPROVED | K1387: =_xlfn.XLOOKUP(B1387,[1]Sheet1!$B:$B,[1]Sheet1!$N:$N,0) -> 0 | L1387: =_xlfn.XLOOKUP(B1387,[1]Sheet1!$B:$B,[1]Sheet1!$O:$O,0) -> 0 | M1387: =_xlfn.XLOOKUP(B1387,[1]Sheet1!$B:$B,[1]Sheet1!$P:$P,0) -> 0 | N1387: =_xlfn.XLOOKUP(B1387,[1]Sheet1!$B:$B,[1]Sheet1!$Q:$Q,0) -> 0 | O1387: =_xlfn.XLOOKUP(B1387,[1]Sheet1!$B:$B,[1]Sheet1!$R:$R,0) -> 0 | P1387: =_xlfn.XLOOKUP(B1387,[1]Sheet1!$B:$B,[1]Sheet1!$S:$S,0) -> 0 | Q1387: =_xlfn.XLOOKUP(B1387,[1]Sheet1!$B:$B,[1]Sheet1!$T:$T,0) -> 0 | R1387: =_xlfn.XLOOKUP(B1387,[1]Sheet1!$B:$B,[1]Sheet1!$U:$U,0) -> 0 | S1387: =_xlfn.XLOOKUP(B1387,[1]Sheet1!$B:$B,[1]Sheet1!$V:$V,0) -> 0 | T1387: =_xlfn.XLOOKUP(B1387,[1]Sheet1!$B:$B,[1]Sheet1!$W:$W,0) -> 0 | U1387: =_xlfn.XLOOKUP(B1387,[1]Sheet1!$B:$B,[1]Sheet1!$X:$X,0) -> 0 | V1387: =_xlfn.XLOOKUP(B1387,[1]Sheet1!$B:$B,[1]Sheet1!$Y:$Y,0) -> 0 | W1387: =SUM(K1387:V1387) -> 0 | X1387: 451.000000.4511010.1.221390.4510000.000000.000.000000.000000 | Y1387: Culture | Z1387: DCT - Culture (Central) Dept | AA1387: 221390 - Other accrued expenses not mentioned elsewhere | AB1387: 000000 - Un Specified | AD1387: 000000 - Unspecified | AE1387: Department of Culture and Tourism | AF1387: DCT Trust Project Type | AG1387: 17131.579 | AH1387: =_xlfn.XLOOKUP(B1387,[1]Sheet1!$B:$B,[1]Sheet1!$AB:$AB,0) -> 0
B1388: =C1388&D1388&F1388&G1388&H1388 -> 45102104514000078Unidentified221390000000 | C1388: 4510210 | D1388: 4514000078 | E1388: ADEO | F1388: Unidentified | G1388: 221390 | H1388: 000000 | I1388: 221390 - Other accrued expenses not mentioned elsewhere | J1388: APPROVED | K1388: =_xlfn.XLOOKUP(B1388,[1]Sheet1!$B:$B,[1]Sheet1!$N:$N,0) -> 0 | L1388: =_xlfn.XLOOKUP(B1388,[1]Sheet1!$B:$B,[1]Sheet1!$O:$O,0) -> 0 | M1388: =_xlfn.XLOOKUP(B1388,[1]Sheet1!$B:$B,[1]Sheet1!$P:$P,0) -> 0 | N1388: =_xlfn.XLOOKUP(B1388,[1]Sheet1!$B:$B,[1]Sheet1!$Q:$Q,0) -> 0 | O1388: =_xlfn.XLOOKUP(B1388,[1]Sheet1!$B:$B,[1]Sheet1!$R:$R,0) -> 0 | P1388: =_xlfn.XLOOKUP(B1388,[1]Sheet1!$B:$B,[1]Sheet1!$S:$S,0) -> 0 | Q1388: =_xlfn.XLOOKUP(B1388,[1]Sheet1!$B:$B,[1]Sheet1!$T:$T,0) -> 0 | R1388: =_xlfn.XLOOKUP(B1388,[1]Sheet1!$B:$B,[1]Sheet1!$U:$U,0) -> 0 | S1388: =_xlfn.XLOOKUP(B1388,[1]Sheet1!$B:$B,[1]Sheet1!$V:$V,0) -> 0 | T1388: =_xlfn.XLOOKUP(B1388,[1]Sheet1!$B:$B,[1]Sheet1!$W:$W,0) -> 0 | U1388: =_xlfn.XLOOKUP(B1388,[1]Sheet1!$B:$B,[1]Sheet1!$X:$X,0) -> 0 | V1388: =_xlfn.XLOOKUP(B1388,[1]Sheet1!$B:$B,[1]Sheet1!$Y:$Y,0) -> 0 | W1388: =SUM(K1388:V1388) -> 0 | X1388: 451.000000.4510210.1.221390.4510000.000000.000.000000.000000 | Y1388: Support Service | Z1388: DCT - Finance Dept | AA1388: 221390 - Other accrued expenses not mentioned elsewhere | AB1388: 000000 - Un Specified | AD1388: 000000 - Unspecified | AE1388: Department of Culture and Tourism | AF1388: DCT Trust Project Type | AG1388: 6632.8358 | AH1388: =_xlfn.XLOOKUP(B1388,[1]Sheet1!$B:$B,[1]Sheet1!$AB:$AB,0) -> 0
B1389: =C1389&D1389&F1389&G1389&H1389 -> 45102104514000084Event Management221390000000 | C1389: 4510210 | D1389: 4514000084 | E1389: My story world | F1389: Event Management | G1389: 221390 | H1389: 000000 | I1389: 221390 - Other accrued expenses not mentioned elsewhere | J1389: APPROVED | K1389: =_xlfn.XLOOKUP(B1389,[1]Sheet1!$B:$B,[1]Sheet1!$N:$N,0) -> 0 | L1389: =_xlfn.XLOOKUP(B1389,[1]Sheet1!$B:$B,[1]Sheet1!$O:$O,0) -> 0 | M1389: =_xlfn.XLOOKUP(B1389,[1]Sheet1!$B:$B,[1]Sheet1!$P:$P,0) -> 0 | N1389: =_xlfn.XLOOKUP(B1389,[1]Sheet1!$B:$B,[1]Sheet1!$Q:$Q,0) -> 0 | O1389: =_xlfn.XLOOKUP(B1389,[1]Sheet1!$B:$B,[1]Sheet1!$R:$R,0) -> 0 | P1389: =_xlfn.XLOOKUP(B1389,[1]Sheet1!$B:$B,[1]Sheet1!$S:$S,0) -> 0 | Q1389: =_xlfn.XLOOKUP(B1389,[1]Sheet1!$B:$B,[1]Sheet1!$T:$T,0) -> 0 | R1389: =_xlfn.XLOOKUP(B1389,[1]Sheet1!$B:$B,[1]Sheet1!$U:$U,0) -> 0 | S1389: =_xlfn.XLOOKUP(B1389,[1]Sheet1!$B:$B,[1]Sheet1!$V:$V,0) -> 0 | T1389: =_xlfn.XLOOKUP(B1389,[1]Sheet1!$B:$B,[1]Sheet1!$W:$W,0) -> 0 | U1389: =_xlfn.XLOOKUP(B1389,[1]Sheet1!$B:$B,[1]Sheet1!$X:$X,0) -> 0 | V1389: =_xlfn.XLOOKUP(B1389,[1]Sheet1!$B:$B,[1]Sheet1!$Y:$Y,0) -> 0 | W1389: =SUM(K1389:V1389) -> 0 | X1389: 451.000000.4510210.1.221390.4510000.000000.000.000000.000000 | Y1389: Support Service | Z1389: DCT - Finance Dept | AA1389: 221390 - Other accrued expenses not mentioned elsewhere | AB1389: 000000 - Un Specified | AD1389: 000000 - Unspecified | AE1389: Department of Culture and Tourism | AF1389: DCT Trust Project Type | AG1389: 910360.88 | AH1389: =_xlfn.XLOOKUP(B1389,[1]Sheet1!$B:$B,[1]Sheet1!$AB:$AB,0) -> 0
B1390: =C1390&D1390&F1390&G1390&H1390 -> 45102104514000086Euro League221390000000 | C1390: 4510210 | D1390: 4514000086 | E1390: Yas Bay Arena | F1390: Euro League | G1390: 221390 | H1390: 000000 | I1390: 221390 - Other accrued expenses not mentioned elsewhere | J1390: APPROVED | K1390: =_xlfn.XLOOKUP(B1390,[1]Sheet1!$B:$B,[1]Sheet1!$N:$N,0) -> 0 | L1390: =_xlfn.XLOOKUP(B1390,[1]Sheet1!$B:$B,[1]Sheet1!$O:$O,0) -> 0 | M1390: =_xlfn.XLOOKUP(B1390,[1]Sheet1!$B:$B,[1]Sheet1!$P:$P,0) -> 0 | N1390: =_xlfn.XLOOKUP(B1390,[1]Sheet1!$B:$B,[1]Sheet1!$Q:$Q,0) -> 0 | O1390: =_xlfn.XLOOKUP(B1390,[1]Sheet1!$B:$B,[1]Sheet1!$R:$R,0) -> 0 | P1390: =_xlfn.XLOOKUP(B1390,[1]Sheet1!$B:$B,[1]Sheet1!$S:$S,0) -> 0 | Q1390: =_xlfn.XLOOKUP(B1390,[1]Sheet1!$B:$B,[1]Sheet1!$T:$T,0) -> 0 | R1390: =_xlfn.XLOOKUP(B1390,[1]Sheet1!$B:$B,[1]Sheet1!$U:$U,0) -> 0 | S1390: =_xlfn.XLOOKUP(B1390,[1]Sheet1!$B:$B,[1]Sheet1!$V:$V,0) -> 0 | T1390: =_xlfn.XLOOKUP(B1390,[1]Sheet1!$B:$B,[1]Sheet1!$W:$W,0) -> 0 | U1390: =_xlfn.XLOOKUP(B1390,[1]Sheet1!$B:$B,[1]Sheet1!$X:$X,0) -> 0 | V1390: =_xlfn.XLOOKUP(B1390,[1]Sheet1!$B:$B,[1]Sheet1!$Y:$Y,0) -> 0 | W1390: =SUM(K1390:V1390) -> 0 | X1390: 451.000000.4510210.1.221390.4510000.000000.000.000000.000000 | Y1390: Support Service | Z1390: DCT - Finance Dept | AA1390: 221390 - Other accrued expenses not mentioned elsewhere | AB1390: 000000 - Un Specified | AD1390: 000000 - Unspecified | AE1390: Department of Culture and Tourism | AF1390: DCT Trust Project Type | AG1390: 3024664.2 | AH1390: =_xlfn.XLOOKUP(B1390,[1]Sheet1!$B:$B,[1]Sheet1!$AB:$AB,0) -> 0
B1391: =C1391&D1391&F1391&G1391&H1391 -> 45102104514000087Extend Stay221390000000 | C1391: 4510210 | D1391: 4514000087 | E1391: Hotel Payments | F1391: Extend Stay | G1391: 221390 | H1391: 000000 | I1391: 221390 - Other accrued expenses not mentioned elsewhere | J1391: APPROVED | K1391: =_xlfn.XLOOKUP(B1391,[1]Sheet1!$B:$B,[1]Sheet1!$N:$N,0) -> 0 | L1391: =_xlfn.XLOOKUP(B1391,[1]Sheet1!$B:$B,[1]Sheet1!$O:$O,0) -> 0 | M1391: =_xlfn.XLOOKUP(B1391,[1]Sheet1!$B:$B,[1]Sheet1!$P:$P,0) -> 0 | N1391: =_xlfn.XLOOKUP(B1391,[1]Sheet1!$B:$B,[1]Sheet1!$Q:$Q,0) -> 0 | O1391: =_xlfn.XLOOKUP(B1391,[1]Sheet1!$B:$B,[1]Sheet1!$R:$R,0) -> 0 | P1391: =_xlfn.XLOOKUP(B1391,[1]Sheet1!$B:$B,[1]Sheet1!$S:$S,0) -> 0 | Q1391: =_xlfn.XLOOKUP(B1391,[1]Sheet1!$B:$B,[1]Sheet1!$T:$T,0) -> 0 | R1391: =_xlfn.XLOOKUP(B1391,[1]Sheet1!$B:$B,[1]Sheet1!$U:$U,0) -> 0 | S1391: =_xlfn.XLOOKUP(B1391,[1]Sheet1!$B:$B,[1]Sheet1!$V:$V,0) -> 0 | T1391: =_xlfn.XLOOKUP(B1391,[1]Sheet1!$B:$B,[1]Sheet1!$W:$W,0) -> 0 | U1391: =_xlfn.XLOOKUP(B1391,[1]Sheet1!$B:$B,[1]Sheet1!$X:$X,0) -> 0 | V1391: =_xlfn.XLOOKUP(B1391,[1]Sheet1!$B:$B,[1]Sheet1!$Y:$Y,0) -> 0 | W1391: =SUM(K1391:V1391) -> 0 | X1391: 451.000000.4510210.1.221390.4510000.000000.000.000000.000000 | Y1391: Support Service | Z1391: DCT - Finance Dept | AA1391: 221390 - Other accrued expenses not mentioned elsewhere | AB1391: 000000 - Un Specified | AD1391: 000000 - Unspecified | AE1391: Department of Culture and Tourism | AF1391: DCT Trust Project Type | AG1391: 4794941.1 | AH1391: =_xlfn.XLOOKUP(B1391,[1]Sheet1!$B:$B,[1]Sheet1!$AB:$AB,0) -> 0
B1392: =C1392&D1392&F1392&G1392&H1392 -> 45102104514000087Privet Host221390000000 | C1392: 4510210 | D1392: 4514000087 | E1392: Hotel Payments | F1392: Privet Host | G1392: 221390 | H1392: 000000 | I1392: 221390 - Other accrued expenses not mentioned elsewhere | J1392: APPROVED | K1392: =_xlfn.XLOOKUP(B1392,[1]Sheet1!$B:$B,[1]Sheet1!$N:$N,0) -> 0 | L1392: =_xlfn.XLOOKUP(B1392,[1]Sheet1!$B:$B,[1]Sheet1!$O:$O,0) -> 0 | M1392: =_xlfn.XLOOKUP(B1392,[1]Sheet1!$B:$B,[1]Sheet1!$P:$P,0) -> 0 | N1392: =_xlfn.XLOOKUP(B1392,[1]Sheet1!$B:$B,[1]Sheet1!$Q:$Q,0) -> 0 | O1392: =_xlfn.XLOOKUP(B1392,[1]Sheet1!$B:$B,[1]Sheet1!$R:$R,0) -> 0 | P1392: =_xlfn.XLOOKUP(B1392,[1]Sheet1!$B:$B,[1]Sheet1!$S:$S,0) -> 0 | Q1392: =_xlfn.XLOOKUP(B1392,[1]Sheet1!$B:$B,[1]Sheet1!$T:$T,0) -> 0 | R1392: =_xlfn.XLOOKUP(B1392,[1]Sheet1!$B:$B,[1]Sheet1!$U:$U,0) -> 0 | S1392: =_xlfn.XLOOKUP(B1392,[1]Sheet1!$B:$B,[1]Sheet1!$V:$V,0) -> 0 | T1392: =_xlfn.XLOOKUP(B1392,[1]Sheet1!$B:$B,[1]Sheet1!$W:$W,0) -> 0 | U1392: =_xlfn.XLOOKUP(B1392,[1]Sheet1!$B:$B,[1]Sheet1!$X:$X,0) -> 0 | V1392: =_xlfn.XLOOKUP(B1392,[1]Sheet1!$B:$B,[1]Sheet1!$Y:$Y,0) -> 0 | W1392: =SUM(K1392:V1392) -> 0 | X1392: 451.000000.4510210.1.221390.4510000.000000.000.000000.000000 | Y1392: Support Service | Z1392: DCT - Finance Dept | AA1392: 221390 - Other accrued expenses not mentioned elsewhere | AB1392: 000000 - Un Specified | AD1392: 000000 - Unspecified | AE1392: Department of Culture and Tourism | AF1392: DCT Trust Project Type | AG1392: 97526743 | AH1392: =_xlfn.XLOOKUP(B1392,[1]Sheet1!$B:$B,[1]Sheet1!$AB:$AB,0) -> 0
B1393: =C1393&D1393&F1393&G1393&H1393 -> 45110104514000088CPC221390000000 | C1393: 4511010 | D1393: 4514000088 | E1393: ADMAF - Trust | F1393: CPC | G1393: 221390 | H1393: 000000 | I1393: 221390 - Other accrued expenses not mentioned elsewhere | J1393: APPROVED | K1393: =_xlfn.XLOOKUP(B1393,[1]Sheet1!$B:$B,[1]Sheet1!$N:$N,0) -> 0 | L1393: =_xlfn.XLOOKUP(B1393,[1]Sheet1!$B:$B,[1]Sheet1!$O:$O,0) -> 0 | M1393: =_xlfn.XLOOKUP(B1393,[1]Sheet1!$B:$B,[1]Sheet1!$P:$P,0) -> 0 | N1393: =_xlfn.XLOOKUP(B1393,[1]Sheet1!$B:$B,[1]Sheet1!$Q:$Q,0) -> 0 | O1393: =_xlfn.XLOOKUP(B1393,[1]Sheet1!$B:$B,[1]Sheet1!$R:$R,0) -> 0 | P1393: =_xlfn.XLOOKUP(B1393,[1]Sheet1!$B:$B,[1]Sheet1!$S:$S,0) -> 0 | Q1393: =_xlfn.XLOOKUP(B1393,[1]Sheet1!$B:$B,[1]Sheet1!$T:$T,0) -> 0 | R1393: =_xlfn.XLOOKUP(B1393,[1]Sheet1!$B:$B,[1]Sheet1!$U:$U,0) -> 0 | S1393: =_xlfn.XLOOKUP(B1393,[1]Sheet1!$B:$B,[1]Sheet1!$V:$V,0) -> 0 | T1393: =_xlfn.XLOOKUP(B1393,[1]Sheet1!$B:$B,[1]Sheet1!$W:$W,0) -> 0 | U1393: =_xlfn.XLOOKUP(B1393,[1]Sheet1!$B:$B,[1]Sheet1!$X:$X,0) -> 0 | V1393: =_xlfn.XLOOKUP(B1393,[1]Sheet1!$B:$B,[1]Sheet1!$Y:$Y,0) -> 0 | W1393: =SUM(K1393:V1393) -> 0 | X1393: 451.000000.4511010.1.221390.4510000.000000.000.000000.000000 | Y1393: Culture | Z1393: DCT - Culture (Central) Dept | AA1393: 221390 - Other accrued expenses not mentioned elsewhere | AB1393: 000000 - Un Specified | AD1393: 000000 - Unspecified | AE1393: Department of Culture and Tourism | AF1393: DCT Trust Project Type | AG1393: 1610677.9 | AH1393: =_xlfn.XLOOKUP(B1393,[1]Sheet1!$B:$B,[1]Sheet1!$AB:$AB,0) -> 0
B1394: =C1394&D1394&F1394&G1394&H1394 -> 45155004514000089Sponsorship Fees221390000000 | C1394: 4515500 | D1394: 4514000089 | E1394: ADSS - Hyrox | F1394: Sponsorship Fees | G1394: 221390 | H1394: 000000 | I1394: 221390 - Other accrued expenses not mentioned elsewhere | J1394: APPROVED | K1394: =_xlfn.XLOOKUP(B1394,[1]Sheet1!$B:$B,[1]Sheet1!$N:$N,0) -> 0 | L1394: =_xlfn.XLOOKUP(B1394,[1]Sheet1!$B:$B,[1]Sheet1!$O:$O,0) -> 0 | M1394: =_xlfn.XLOOKUP(B1394,[1]Sheet1!$B:$B,[1]Sheet1!$P:$P,0) -> 0 | N1394: =_xlfn.XLOOKUP(B1394,[1]Sheet1!$B:$B,[1]Sheet1!$Q:$Q,0) -> 0 | O1394: =_xlfn.XLOOKUP(B1394,[1]Sheet1!$B:$B,[1]Sheet1!$R:$R,0) -> 0 | P1394: =_xlfn.XLOOKUP(B1394,[1]Sheet1!$B:$B,[1]Sheet1!$S:$S,0) -> 0 | Q1394: =_xlfn.XLOOKUP(B1394,[1]Sheet1!$B:$B,[1]Sheet1!$T:$T,0) -> 0 | R1394: =_xlfn.XLOOKUP(B1394,[1]Sheet1!$B:$B,[1]Sheet1!$U:$U,0) -> 0 | S1394: =_xlfn.XLOOKUP(B1394,[1]Sheet1!$B:$B,[1]Sheet1!$V:$V,0) -> 0 | T1394: =_xlfn.XLOOKUP(B1394,[1]Sheet1!$B:$B,[1]Sheet1!$W:$W,0) -> 0 | U1394: =_xlfn.XLOOKUP(B1394,[1]Sheet1!$B:$B,[1]Sheet1!$X:$X,0) -> 0 | V1394: =_xlfn.XLOOKUP(B1394,[1]Sheet1!$B:$B,[1]Sheet1!$Y:$Y,0) -> 0 | W1394: =SUM(K1394:V1394) -> 0 | X1394: 451.000000.4515500.1.221390.4510000.000000.000.000000.000000 | Y1394: Tourism | Z1394: DCT - Abu Dhabi Events Bureau | AA1394: 221390 - Other accrued expenses not mentioned elsewhere | AB1394: 000000 - Un Specified | AD1394: 000000 - Unspecified | AE1394: Department of Culture and Tourism | AF1394: DCT Trust Project Type | AG1394: 794689.2 | AH1394: =_xlfn.XLOOKUP(B1394,[1]Sheet1!$B:$B,[1]Sheet1!$AB:$AB,0) -> 0
B1395: =C1395&D1395&F1395&G1395&H1395 -> 451400045170000014510789424521200104 | C1395: 4514000 | D1395: 4517000001 | E1395: Museums - Director's Office | F1395: 4510789 | G1395: 424521 | H1395: 200104 | I1395: 424521 - Manpower supply Other Than IT Related | J1395: APPROVED | K1395: =_xlfn.XLOOKUP(B1395,[1]Sheet1!$B:$B,[1]Sheet1!$N:$N,0) -> 0 | L1395: =_xlfn.XLOOKUP(B1395,[1]Sheet1!$B:$B,[1]Sheet1!$O:$O,0) -> 0 | M1395: =_xlfn.XLOOKUP(B1395,[1]Sheet1!$B:$B,[1]Sheet1!$P:$P,0) -> 0 | N1395: =_xlfn.XLOOKUP(B1395,[1]Sheet1!$B:$B,[1]Sheet1!$Q:$Q,0) -> 0 | O1395: =_xlfn.XLOOKUP(B1395,[1]Sheet1!$B:$B,[1]Sheet1!$R:$R,0) -> 0 | P1395: =_xlfn.XLOOKUP(B1395,[1]Sheet1!$B:$B,[1]Sheet1!$S:$S,0) -> 0 | Q1395: =_xlfn.XLOOKUP(B1395,[1]Sheet1!$B:$B,[1]Sheet1!$T:$T,0) -> 0 | R1395: =_xlfn.XLOOKUP(B1395,[1]Sheet1!$B:$B,[1]Sheet1!$U:$U,0) -> 0 | S1395: =_xlfn.XLOOKUP(B1395,[1]Sheet1!$B:$B,[1]Sheet1!$V:$V,0) -> 0 | T1395: =_xlfn.XLOOKUP(B1395,[1]Sheet1!$B:$B,[1]Sheet1!$W:$W,0) -> 0 | U1395: =_xlfn.XLOOKUP(B1395,[1]Sheet1!$B:$B,[1]Sheet1!$X:$X,0) -> 0 | V1395: =_xlfn.XLOOKUP(B1395,[1]Sheet1!$B:$B,[1]Sheet1!$Y:$Y,0) -> 0 | W1395: =SUM(K1395:V1395) -> 0 | X1395: 451.070101.4514000.1.424521.4510700.200104.000.000000.000000 | Y1395: Museum Shared Services | Z1395: Museums - Director’s Office | AA1395: 424521 - Manpower supply Other Than IT Related | AB1395: 200104 - FA104-Opex Expense | AC1395: Chapter 2 | AD1395: 070101 - Corporate Office | AE1395: Museum Shared Services | AF1395: MSS OPEX Project Type | AG1395: 420000 | AH1395: =_xlfn.XLOOKUP(B1395,[1]Sheet1!$B:$B,[1]Sheet1!$AB:$AB,0) -> 0
B1396: =C1396&D1396&F1396&G1396&H1396 -> 451400045170000014510808421122200104 | C1396: 4514000 | D1396: 4517000001 | E1396: Museums - Director's Office | F1396: 4510808 | G1396: 421122 | H1396: 200104 | I1396: 421122 - Management consultancy expenses | J1396: APPROVED | K1396: =_xlfn.XLOOKUP(B1396,[1]Sheet1!$B:$B,[1]Sheet1!$N:$N,0) -> 0 | L1396: =_xlfn.XLOOKUP(B1396,[1]Sheet1!$B:$B,[1]Sheet1!$O:$O,0) -> 0 | M1396: =_xlfn.XLOOKUP(B1396,[1]Sheet1!$B:$B,[1]Sheet1!$P:$P,0) -> 0 | N1396: =_xlfn.XLOOKUP(B1396,[1]Sheet1!$B:$B,[1]Sheet1!$Q:$Q,0) -> 0 | O1396: =_xlfn.XLOOKUP(B1396,[1]Sheet1!$B:$B,[1]Sheet1!$R:$R,0) -> 0 | P1396: =_xlfn.XLOOKUP(B1396,[1]Sheet1!$B:$B,[1]Sheet1!$S:$S,0) -> 0 | Q1396: =_xlfn.XLOOKUP(B1396,[1]Sheet1!$B:$B,[1]Sheet1!$T:$T,0) -> 0 | R1396: =_xlfn.XLOOKUP(B1396,[1]Sheet1!$B:$B,[1]Sheet1!$U:$U,0) -> 0 | S1396: =_xlfn.XLOOKUP(B1396,[1]Sheet1!$B:$B,[1]Sheet1!$V:$V,0) -> 0 | T1396: =_xlfn.XLOOKUP(B1396,[1]Sheet1!$B:$B,[1]Sheet1!$W:$W,0) -> 0 | U1396: =_xlfn.XLOOKUP(B1396,[1]Sheet1!$B:$B,[1]Sheet1!$X:$X,0) -> 0 | V1396: =_xlfn.XLOOKUP(B1396,[1]Sheet1!$B:$B,[1]Sheet1!$Y:$Y,0) -> 0 | W1396: =SUM(K1396:V1396) -> 0 | X1396: 451.070101.4514000.1.421122.4510700.200104.000.000000.000000 | Y1396: Museum Shared Services | Z1396: Museums - Director’s Office | AA1396: 421122 - Management consultancy expenses | AB1396: 200104 - FA104-Opex Expense | AC1396: Chapter 2 | AD1396: 070101 - Corporate Office | AE1396: Museum Shared Services | AF1396: MSS OPEX Project Type | AG1396: 525000 | AH1396: =_xlfn.XLOOKUP(B1396,[1]Sheet1!$B:$B,[1]Sheet1!$AB:$AB,0) -> 0
B1397: =C1397&D1397&F1397&G1397&H1397 -> 451412045170000024510723424521200104 | C1397: 4514120 | D1397: 4517000002 | E1397: Museums - Finance Planning and Business Partnership | F1397: 4510723 | G1397: 424521 | H1397: 200104 | I1397: 424521 - Manpower supply Other Than IT Related | J1397: APPROVED | K1397: =_xlfn.XLOOKUP(B1397,[1]Sheet1!$B:$B,[1]Sheet1!$N:$N,0) -> 0 | L1397: =_xlfn.XLOOKUP(B1397,[1]Sheet1!$B:$B,[1]Sheet1!$O:$O,0) -> 0 | M1397: =_xlfn.XLOOKUP(B1397,[1]Sheet1!$B:$B,[1]Sheet1!$P:$P,0) -> 0 | N1397: =_xlfn.XLOOKUP(B1397,[1]Sheet1!$B:$B,[1]Sheet1!$Q:$Q,0) -> 0 | O1397: =_xlfn.XLOOKUP(B1397,[1]Sheet1!$B:$B,[1]Sheet1!$R:$R,0) -> 0 | P1397: =_xlfn.XLOOKUP(B1397,[1]Sheet1!$B:$B,[1]Sheet1!$S:$S,0) -> 0 | Q1397: =_xlfn.XLOOKUP(B1397,[1]Sheet1!$B:$B,[1]Sheet1!$T:$T,0) -> 0 | R1397: =_xlfn.XLOOKUP(B1397,[1]Sheet1!$B:$B,[1]Sheet1!$U:$U,0) -> 0 | S1397: =_xlfn.XLOOKUP(B1397,[1]Sheet1!$B:$B,[1]Sheet1!$V:$V,0) -> 0 | T1397: =_xlfn.XLOOKUP(B1397,[1]Sheet1!$B:$B,[1]Sheet1!$W:$W,0) -> 0 | U1397: =_xlfn.XLOOKUP(B1397,[1]Sheet1!$B:$B,[1]Sheet1!$X:$X,0) -> 0 | V1397: =_xlfn.XLOOKUP(B1397,[1]Sheet1!$B:$B,[1]Sheet1!$Y:$Y,0) -> 0 | W1397: =SUM(K1397:V1397) -> 0 | X1397: 451.070103.4514120.1.424521.4510700.200104.000.000000.000000 | Y1397: Museum Shared Services | Z1397: Museums - Finance | AA1397: 424521 - Manpower supply Other Than IT Related | AB1397: 200104 - FA104-Opex Expense | AC1397: Chapter 2 | AD1397: 070103 - Human Resource (HR) | AE1397: Museum Shared Services | AF1397: MSS OPEX Project Type | AG1397: 774000 | AH1397: =_xlfn.XLOOKUP(B1397,[1]Sheet1!$B:$B,[1]Sheet1!$AB:$AB,0) -> 0
B1398: =C1398&D1398&F1398&G1398&H1398 -> 451412045170000034510715437111200104 | C1398: 4514120 | D1398: 4517000003 | E1398: Museums - Finance Operations | F1398: 4510715 | G1398: 437111 | H1398: 200104 | I1398: 437111 - Banking service charges | J1398: APPROVED | K1398: =_xlfn.XLOOKUP(B1398,[1]Sheet1!$B:$B,[1]Sheet1!$N:$N,0) -> 0 | L1398: =_xlfn.XLOOKUP(B1398,[1]Sheet1!$B:$B,[1]Sheet1!$O:$O,0) -> 0 | M1398: =_xlfn.XLOOKUP(B1398,[1]Sheet1!$B:$B,[1]Sheet1!$P:$P,0) -> 0 | N1398: =_xlfn.XLOOKUP(B1398,[1]Sheet1!$B:$B,[1]Sheet1!$Q:$Q,0) -> 0 | O1398: =_xlfn.XLOOKUP(B1398,[1]Sheet1!$B:$B,[1]Sheet1!$R:$R,0) -> 0 | P1398: =_xlfn.XLOOKUP(B1398,[1]Sheet1!$B:$B,[1]Sheet1!$S:$S,0) -> 0 | Q1398: =_xlfn.XLOOKUP(B1398,[1]Sheet1!$B:$B,[1]Sheet1!$T:$T,0) -> 0 | R1398: =_xlfn.XLOOKUP(B1398,[1]Sheet1!$B:$B,[1]Sheet1!$U:$U,0) -> 0 | S1398: =_xlfn.XLOOKUP(B1398,[1]Sheet1!$B:$B,[1]Sheet1!$V:$V,0) -> 0 | T1398: =_xlfn.XLOOKUP(B1398,[1]Sheet1!$B:$B,[1]Sheet1!$W:$W,0) -> 0 | U1398: =_xlfn.XLOOKUP(B1398,[1]Sheet1!$B:$B,[1]Sheet1!$X:$X,0) -> 0 | V1398: =_xlfn.XLOOKUP(B1398,[1]Sheet1!$B:$B,[1]Sheet1!$Y:$Y,0) -> 0 | W1398: =SUM(K1398:V1398) -> 0 | X1398: 451.070102.4514120.1.437111.4510700.200104.000.000000.000000 | Y1398: Museum Shared Services | Z1398: Museums - Finance | AA1398: 437111 - Banking service charges | AB1398: 200104 - FA104-Opex Expense | AC1398: Chapter 2 | AD1398: 070102 - Finance | AE1398: Museum Shared Services | AF1398: MSS OPEX Project Type | AG1398: 3063927 | AH1398: =_xlfn.XLOOKUP(B1398,[1]Sheet1!$B:$B,[1]Sheet1!$AB:$AB,0) -> 0
B1399: =C1399&D1399&F1399&G1399&H1399 -> 451412045170000034510720421112200104 | C1399: 4514120 | D1399: 4517000003 | E1399: Museums - Finance Operations | F1399: 4510720 | G1399: 421112 | H1399: 200104 | I1399: 421112 - Internal Audit service expenses | J1399: APPROVED | K1399: =_xlfn.XLOOKUP(B1399,[1]Sheet1!$B:$B,[1]Sheet1!$N:$N,0) -> 0 | L1399: =_xlfn.XLOOKUP(B1399,[1]Sheet1!$B:$B,[1]Sheet1!$O:$O,0) -> 0 | M1399: =_xlfn.XLOOKUP(B1399,[1]Sheet1!$B:$B,[1]Sheet1!$P:$P,0) -> 0 | N1399: =_xlfn.XLOOKUP(B1399,[1]Sheet1!$B:$B,[1]Sheet1!$Q:$Q,0) -> 0 | O1399: =_xlfn.XLOOKUP(B1399,[1]Sheet1!$B:$B,[1]Sheet1!$R:$R,0) -> 0 | P1399: =_xlfn.XLOOKUP(B1399,[1]Sheet1!$B:$B,[1]Sheet1!$S:$S,0) -> 0 | Q1399: =_xlfn.XLOOKUP(B1399,[1]Sheet1!$B:$B,[1]Sheet1!$T:$T,0) -> 0 | R1399: =_xlfn.XLOOKUP(B1399,[1]Sheet1!$B:$B,[1]Sheet1!$U:$U,0) -> 0 | S1399: =_xlfn.XLOOKUP(B1399,[1]Sheet1!$B:$B,[1]Sheet1!$V:$V,0) -> 0 | T1399: =_xlfn.XLOOKUP(B1399,[1]Sheet1!$B:$B,[1]Sheet1!$W:$W,0) -> 0 | U1399: =_xlfn.XLOOKUP(B1399,[1]Sheet1!$B:$B,[1]Sheet1!$X:$X,0) -> 0 | V1399: =_xlfn.XLOOKUP(B1399,[1]Sheet1!$B:$B,[1]Sheet1!$Y:$Y,0) -> 0 | W1399: =SUM(K1399:V1399) -> 0 | X1399: 451.070102.4514120.1.421112.4510700.200104.000.000000.000000 | Y1399: Museum Shared Services | Z1399: Museums - Finance | AA1399: 421112 - Internal Audit service expenses | AB1399: 200104 - FA104-Opex Expense | AC1399: Chapter 2 | AD1399: 070102 - Finance | AE1399: Museum Shared Services | AF1399: MSS OPEX Project Type | AG1399: 1291794 | AH1399: =_xlfn.XLOOKUP(B1399,[1]Sheet1!$B:$B,[1]Sheet1!$AB:$AB,0) -> 0
B1400: =C1400&D1400&F1400&G1400&H1400 -> 451412045170000044510723424521200104 | C1400: 4514120 | D1400: 4517000004 | E1400: Museums - Payables Operations | F1400: 4510723 | G1400: 424521 | H1400: 200104 | I1400: 424521 - Manpower supply Other Than IT Related | J1400: APPROVED | K1400: =_xlfn.XLOOKUP(B1400,[1]Sheet1!$B:$B,[1]Sheet1!$N:$N,0) -> 0 | L1400: =_xlfn.XLOOKUP(B1400,[1]Sheet1!$B:$B,[1]Sheet1!$O:$O,0) -> 0 | M1400: =_xlfn.XLOOKUP(B1400,[1]Sheet1!$B:$B,[1]Sheet1!$P:$P,0) -> 0 | N1400: =_xlfn.XLOOKUP(B1400,[1]Sheet1!$B:$B,[1]Sheet1!$Q:$Q,0) -> 0 | O1400: =_xlfn.XLOOKUP(B1400,[1]Sheet1!$B:$B,[1]Sheet1!$R:$R,0) -> 0 | P1400: =_xlfn.XLOOKUP(B1400,[1]Sheet1!$B:$B,[1]Sheet1!$S:$S,0) -> 0 | Q1400: =_xlfn.XLOOKUP(B1400,[1]Sheet1!$B:$B,[1]Sheet1!$T:$T,0) -> 0 | R1400: =_xlfn.XLOOKUP(B1400,[1]Sheet1!$B:$B,[1]Sheet1!$U:$U,0) -> 0 | S1400: =_xlfn.XLOOKUP(B1400,[1]Sheet1!$B:$B,[1]Sheet1!$V:$V,0) -> 0 | T1400: =_xlfn.XLOOKUP(B1400,[1]Sheet1!$B:$B,[1]Sheet1!$W:$W,0) -> 0 | U1400: =_xlfn.XLOOKUP(B1400,[1]Sheet1!$B:$B,[1]Sheet1!$X:$X,0) -> 0 | V1400: =_xlfn.XLOOKUP(B1400,[1]Sheet1!$B:$B,[1]Sheet1!$Y:$Y,0) -> 0 | W1400: =SUM(K1400:V1400) -> 0 | X1400: 451.070103.4514120.1.424521.4510700.200104.000.000000.000000 | Y1400: Museum Shared Services | Z1400: Museums - Finance | AA1400: 424521 - Manpower supply Other Than IT Related | AB1400: 200104 - FA104-Opex Expense | AC1400: Chapter 2 | AD1400: 070103 - Human Resource (HR) | AE1400: Museum Shared Services | AF1400: MSS OPEX Project Type | AG1400: 660000 | AH1400: =_xlfn.XLOOKUP(B1400,[1]Sheet1!$B:$B,[1]Sheet1!$AB:$AB,0) -> 0
B1401: =C1401&D1401&F1401&G1401&H1401 -> 451412045170000054510723424521200104 | C1401: 4514120 | D1401: 4517000005 | E1401: Museums - Receivables Operations | F1401: 4510723 | G1401: 424521 | H1401: 200104 | I1401: 424521 - Manpower supply Other Than IT Related | J1401: APPROVED | K1401: =_xlfn.XLOOKUP(B1401,[1]Sheet1!$B:$B,[1]Sheet1!$N:$N,0) -> 0 | L1401: =_xlfn.XLOOKUP(B1401,[1]Sheet1!$B:$B,[1]Sheet1!$O:$O,0) -> 0 | M1401: =_xlfn.XLOOKUP(B1401,[1]Sheet1!$B:$B,[1]Sheet1!$P:$P,0) -> 0 | N1401: =_xlfn.XLOOKUP(B1401,[1]Sheet1!$B:$B,[1]Sheet1!$Q:$Q,0) -> 0 | O1401: =_xlfn.XLOOKUP(B1401,[1]Sheet1!$B:$B,[1]Sheet1!$R:$R,0) -> 0 | P1401: =_xlfn.XLOOKUP(B1401,[1]Sheet1!$B:$B,[1]Sheet1!$S:$S,0) -> 0 | Q1401: =_xlfn.XLOOKUP(B1401,[1]Sheet1!$B:$B,[1]Sheet1!$T:$T,0) -> 0 | R1401: =_xlfn.XLOOKUP(B1401,[1]Sheet1!$B:$B,[1]Sheet1!$U:$U,0) -> 0 | S1401: =_xlfn.XLOOKUP(B1401,[1]Sheet1!$B:$B,[1]Sheet1!$V:$V,0) -> 0 | T1401: =_xlfn.XLOOKUP(B1401,[1]Sheet1!$B:$B,[1]Sheet1!$W:$W,0) -> 0 | U1401: =_xlfn.XLOOKUP(B1401,[1]Sheet1!$B:$B,[1]Sheet1!$X:$X,0) -> 0 | V1401: =_xlfn.XLOOKUP(B1401,[1]Sheet1!$B:$B,[1]Sheet1!$Y:$Y,0) -> 0 | W1401: =SUM(K1401:V1401) -> 0 | X1401: 451.070102.4514120.1.424521.4510700.200104.000.000000.000000 | Y1401: Museum Shared Services | Z1401: Museums - Finance | AA1401: 424521 - Manpower supply Other Than IT Related | AB1401: 200104 - FA104-Opex Expense | AC1401: Chapter 2 | AD1401: 070102 - Finance | AE1401: Museum Shared Services | AF1401: MSS OPEX Project Type | AG1401: 240000 | AH1401: =_xlfn.XLOOKUP(B1401,[1]Sheet1!$B:$B,[1]Sheet1!$AB:$AB,0) -> 0
B1402: =C1402&D1402&F1402&G1402&H1402 -> 451412045170000054510750424521200104 | C1402: 4514120 | D1402: 4517000005 | E1402: Museums - Receivables Operations | F1402: 4510750 | G1402: 424521 | H1402: 200104 | I1402: 424521 - Manpower supply Other Than IT Related | J1402: APPROVED | K1402: =_xlfn.XLOOKUP(B1402,[1]Sheet1!$B:$B,[1]Sheet1!$N:$N,0) -> 0 | L1402: =_xlfn.XLOOKUP(B1402,[1]Sheet1!$B:$B,[1]Sheet1!$O:$O,0) -> 0 | M1402: =_xlfn.XLOOKUP(B1402,[1]Sheet1!$B:$B,[1]Sheet1!$P:$P,0) -> 0 | N1402: =_xlfn.XLOOKUP(B1402,[1]Sheet1!$B:$B,[1]Sheet1!$Q:$Q,0) -> 0 | O1402: =_xlfn.XLOOKUP(B1402,[1]Sheet1!$B:$B,[1]Sheet1!$R:$R,0) -> 0 | P1402: =_xlfn.XLOOKUP(B1402,[1]Sheet1!$B:$B,[1]Sheet1!$S:$S,0) -> 0 | Q1402: =_xlfn.XLOOKUP(B1402,[1]Sheet1!$B:$B,[1]Sheet1!$T:$T,0) -> 0 | R1402: =_xlfn.XLOOKUP(B1402,[1]Sheet1!$B:$B,[1]Sheet1!$U:$U,0) -> 0 | S1402: =_xlfn.XLOOKUP(B1402,[1]Sheet1!$B:$B,[1]Sheet1!$V:$V,0) -> 0 | T1402: =_xlfn.XLOOKUP(B1402,[1]Sheet1!$B:$B,[1]Sheet1!$W:$W,0) -> 0 | U1402: =_xlfn.XLOOKUP(B1402,[1]Sheet1!$B:$B,[1]Sheet1!$X:$X,0) -> 0 | V1402: =_xlfn.XLOOKUP(B1402,[1]Sheet1!$B:$B,[1]Sheet1!$Y:$Y,0) -> 0 | W1402: =SUM(K1402:V1402) -> 0 | X1402: 451.070103.4514120.1.424521.4510700.200104.000.000000.000000 | Y1402: Museum Shared Services | Z1402: Museums - Finance | AA1402: 424521 - Manpower supply Other Than IT Related | AB1402: 200104 - FA104-Opex Expense | AC1402: Chapter 2 | AD1402: 070103 - Human Resource (HR) | AE1402: Museum Shared Services | AF1402: MSS OPEX Project Type | AG1402: 316206 | AH1402: =_xlfn.XLOOKUP(B1402,[1]Sheet1!$B:$B,[1]Sheet1!$AB:$AB,0) -> 0
B1403: =C1403&D1403&F1403&G1403&H1403 -> 451414045170000074510723424521200104 | C1403: 4514140 | D1403: 4517000007 | E1403: Museums - Talent Development | F1403: 4510723 | G1403: 424521 | H1403: 200104 | I1403: 424521 - Manpower supply Other Than IT Related | J1403: APPROVED | K1403: =_xlfn.XLOOKUP(B1403,[1]Sheet1!$B:$B,[1]Sheet1!$N:$N,0) -> 0 | L1403: =_xlfn.XLOOKUP(B1403,[1]Sheet1!$B:$B,[1]Sheet1!$O:$O,0) -> 0 | M1403: =_xlfn.XLOOKUP(B1403,[1]Sheet1!$B:$B,[1]Sheet1!$P:$P,0) -> 0 | N1403: =_xlfn.XLOOKUP(B1403,[1]Sheet1!$B:$B,[1]Sheet1!$Q:$Q,0) -> 0 | O1403: =_xlfn.XLOOKUP(B1403,[1]Sheet1!$B:$B,[1]Sheet1!$R:$R,0) -> 0 | P1403: =_xlfn.XLOOKUP(B1403,[1]Sheet1!$B:$B,[1]Sheet1!$S:$S,0) -> 0 | Q1403: =_xlfn.XLOOKUP(B1403,[1]Sheet1!$B:$B,[1]Sheet1!$T:$T,0) -> 0 | R1403: =_xlfn.XLOOKUP(B1403,[1]Sheet1!$B:$B,[1]Sheet1!$U:$U,0) -> 0 | S1403: =_xlfn.XLOOKUP(B1403,[1]Sheet1!$B:$B,[1]Sheet1!$V:$V,0) -> 0 | T1403: =_xlfn.XLOOKUP(B1403,[1]Sheet1!$B:$B,[1]Sheet1!$W:$W,0) -> 0 | U1403: =_xlfn.XLOOKUP(B1403,[1]Sheet1!$B:$B,[1]Sheet1!$X:$X,0) -> 0 | V1403: =_xlfn.XLOOKUP(B1403,[1]Sheet1!$B:$B,[1]Sheet1!$Y:$Y,0) -> 0 | W1403: =SUM(K1403:V1403) -> 0 | X1403: 451.070103.4514140.1.424521.4510700.200104.000.000000.000000 | Y1403: Museum Shared Services | Z1403: Museums - People and Performance | AA1403: 424521 - Manpower supply Other Than IT Related | AB1403: 200104 - FA104-Opex Expense | AC1403: Chapter 2 | AD1403: 070103 - Human Resource (HR) | AE1403: Museum Shared Services | AF1403: MSS OPEX Project Type | AG1403: 582444 | AH1403: =_xlfn.XLOOKUP(B1403,[1]Sheet1!$B:$B,[1]Sheet1!$AB:$AB,0) -> 0
B1404: =C1404&D1404&F1404&G1404&H1404 -> 451414045170000074510802413710100103 | C1404: 4514140 | D1404: 4517000007 | E1404: Museums - Talent Development | F1404: 4510802 | G1404: 413710 | H1404: 100103 | I1404: 413710 - Tuition fees Non IT Related | J1404: APPROVED | K1404: =_xlfn.XLOOKUP(B1404,[1]Sheet1!$B:$B,[1]Sheet1!$N:$N,0) -> 0 | L1404: =_xlfn.XLOOKUP(B1404,[1]Sheet1!$B:$B,[1]Sheet1!$O:$O,0) -> 0 | M1404: =_xlfn.XLOOKUP(B1404,[1]Sheet1!$B:$B,[1]Sheet1!$P:$P,0) -> 0 | N1404: =_xlfn.XLOOKUP(B1404,[1]Sheet1!$B:$B,[1]Sheet1!$Q:$Q,0) -> 0 | O1404: =_xlfn.XLOOKUP(B1404,[1]Sheet1!$B:$B,[1]Sheet1!$R:$R,0) -> 0 | P1404: =_xlfn.XLOOKUP(B1404,[1]Sheet1!$B:$B,[1]Sheet1!$S:$S,0) -> 0 | Q1404: =_xlfn.XLOOKUP(B1404,[1]Sheet1!$B:$B,[1]Sheet1!$T:$T,0) -> 0 | R1404: =_xlfn.XLOOKUP(B1404,[1]Sheet1!$B:$B,[1]Sheet1!$U:$U,0) -> 0 | S1404: =_xlfn.XLOOKUP(B1404,[1]Sheet1!$B:$B,[1]Sheet1!$V:$V,0) -> 0 | T1404: =_xlfn.XLOOKUP(B1404,[1]Sheet1!$B:$B,[1]Sheet1!$W:$W,0) -> 0 | U1404: =_xlfn.XLOOKUP(B1404,[1]Sheet1!$B:$B,[1]Sheet1!$X:$X,0) -> 0 | V1404: =_xlfn.XLOOKUP(B1404,[1]Sheet1!$B:$B,[1]Sheet1!$Y:$Y,0) -> 0 | W1404: =SUM(K1404:V1404) -> 0 | X1404: 451.070103.4514140.1.413710.4510700.100103.000.000000.000000 | Y1404: Museum Shared Services | Z1404: Museums - People and Performance | AA1404: 413710 - Tuition fees "Other Than IT Related" | AB1404: 100103 - FA103-Manpower Expense | AC1404: Chapter 1 | AD1404: 070103 - Human Resource (HR) | AE1404: Museum Shared Services | AF1404: MSS OPEX Project Type | AG1404: 2130000 | AH1404: =_xlfn.XLOOKUP(B1404,[1]Sheet1!$B:$B,[1]Sheet1!$AB:$AB,0) -> 0
B1405: =C1405&D1405&F1405&G1405&H1405 -> 451414045170000084510723424521200104 | C1405: 4514140 | D1405: 4517000008 | E1405: Museums - P&P Operations | F1405: 4510723 | G1405: 424521 | H1405: 200104 | I1405: 424521 - Manpower supply Other Than IT Related | J1405: APPROVED | K1405: =_xlfn.XLOOKUP(B1405,[1]Sheet1!$B:$B,[1]Sheet1!$N:$N,0) -> 0 | L1405: =_xlfn.XLOOKUP(B1405,[1]Sheet1!$B:$B,[1]Sheet1!$O:$O,0) -> 0 | M1405: =_xlfn.XLOOKUP(B1405,[1]Sheet1!$B:$B,[1]Sheet1!$P:$P,0) -> 0 | N1405: =_xlfn.XLOOKUP(B1405,[1]Sheet1!$B:$B,[1]Sheet1!$Q:$Q,0) -> 0 | O1405: =_xlfn.XLOOKUP(B1405,[1]Sheet1!$B:$B,[1]Sheet1!$R:$R,0) -> 0 | P1405: =_xlfn.XLOOKUP(B1405,[1]Sheet1!$B:$B,[1]Sheet1!$S:$S,0) -> 0 | Q1405: =_xlfn.XLOOKUP(B1405,[1]Sheet1!$B:$B,[1]Sheet1!$T:$T,0) -> 0 | R1405: =_xlfn.XLOOKUP(B1405,[1]Sheet1!$B:$B,[1]Sheet1!$U:$U,0) -> 0 | S1405: =_xlfn.XLOOKUP(B1405,[1]Sheet1!$B:$B,[1]Sheet1!$V:$V,0) -> 0 | T1405: =_xlfn.XLOOKUP(B1405,[1]Sheet1!$B:$B,[1]Sheet1!$W:$W,0) -> 0 | U1405: =_xlfn.XLOOKUP(B1405,[1]Sheet1!$B:$B,[1]Sheet1!$X:$X,0) -> 0 | V1405: =_xlfn.XLOOKUP(B1405,[1]Sheet1!$B:$B,[1]Sheet1!$Y:$Y,0) -> 0 | W1405: =SUM(K1405:V1405) -> 0 | X1405: 451.070103.4514140.1.424521.4510700.200104.000.000000.000000 | Y1405: Museum Shared Services | Z1405: Museums - People and Performance | AA1405: 424521 - Manpower supply Other Than IT Related | AB1405: 200104 - FA104-Opex Expense | AC1405: Chapter 2 | AD1405: 070103 - Human Resource (HR) | AE1405: Museum Shared Services | AF1405: MSS OPEX Project Type | AG1405: 1084569 | AH1405: =_xlfn.XLOOKUP(B1405,[1]Sheet1!$B:$B,[1]Sheet1!$AB:$AB,0) -> 0
B1406: =C1406&D1406&F1406&G1406&H1406 -> 451418045170000084510725424231200104 | C1406: 4514180 | D1406: 4517000008 | E1406: Museums - P&P Operations | F1406: 4510725 | G1406: 424231 | H1406: 200104 | I1406: 424231 - Events - Awards, prizes and gifts | J1406: APPROVED | K1406: =_xlfn.XLOOKUP(B1406,[1]Sheet1!$B:$B,[1]Sheet1!$N:$N,0) -> 0 | L1406: =_xlfn.XLOOKUP(B1406,[1]Sheet1!$B:$B,[1]Sheet1!$O:$O,0) -> 0 | M1406: =_xlfn.XLOOKUP(B1406,[1]Sheet1!$B:$B,[1]Sheet1!$P:$P,0) -> 0 | N1406: =_xlfn.XLOOKUP(B1406,[1]Sheet1!$B:$B,[1]Sheet1!$Q:$Q,0) -> 0 | O1406: =_xlfn.XLOOKUP(B1406,[1]Sheet1!$B:$B,[1]Sheet1!$R:$R,0) -> 0 | P1406: =_xlfn.XLOOKUP(B1406,[1]Sheet1!$B:$B,[1]Sheet1!$S:$S,0) -> 0 | Q1406: =_xlfn.XLOOKUP(B1406,[1]Sheet1!$B:$B,[1]Sheet1!$T:$T,0) -> 0 | R1406: =_xlfn.XLOOKUP(B1406,[1]Sheet1!$B:$B,[1]Sheet1!$U:$U,0) -> 0 | S1406: =_xlfn.XLOOKUP(B1406,[1]Sheet1!$B:$B,[1]Sheet1!$V:$V,0) -> 0 | T1406: =_xlfn.XLOOKUP(B1406,[1]Sheet1!$B:$B,[1]Sheet1!$W:$W,0) -> 0 | U1406: =_xlfn.XLOOKUP(B1406,[1]Sheet1!$B:$B,[1]Sheet1!$X:$X,0) -> 0 | V1406: =_xlfn.XLOOKUP(B1406,[1]Sheet1!$B:$B,[1]Sheet1!$Y:$Y,0) -> 0 | W1406: =SUM(K1406:V1406) -> 0 | X1406: 451.070103.4514180.1.424231.4510700.200104.000.000000.000000 | Y1406: Museum Shared Services | Z1406: Museums - People and Performance | AA1406: 424231 - Events - Awards, prizes & gifts | AB1406: 200104 - FA104-Opex Expense | AC1406: Chapter 2 | AD1406: 070103 - Human Resource (HR) | AE1406: Museum Shared Services | AF1406: MSS OPEX Project Type | AG1406: 1840450 | AH1406: =_xlfn.XLOOKUP(B1406,[1]Sheet1!$B:$B,[1]Sheet1!$AB:$AB,0) -> 0
... B1741: =C1741&D1741&F1741&G1741&H1741 -> 451400045170001104510820491811300105 | C1741: 4514000 | D1741: 4517000110 | E1741: Museum's Operations | F1741: 4510820 | G1741: 491811 | H1741: 300105 | I1741: 491811 - Heritage culture assts | J1741: APPROVED | K1741: =_xlfn.XLOOKUP(B1741,[1]Sheet1!$B:$B,[1]Sheet1!$N:$N,0) -> 0 | L1741: =_xlfn.XLOOKUP(B1741,[1]Sheet1!$B:$B,[1]Sheet1!$O:$O,0) -> 0 | M1741: =_xlfn.XLOOKUP(B1741,[1]Sheet1!$B:$B,[1]Sheet1!$P:$P,0) -> 0 | N1741: =_xlfn.XLOOKUP(B1741,[1]Sheet1!$B:$B,[1]Sheet1!$Q:$Q,0) -> 0 | O1741: =_xlfn.XLOOKUP(B1741,[1]Sheet1!$B:$B,[1]Sheet1!$R:$R,0) -> 0 | P1741: =_xlfn.XLOOKUP(B1741,[1]Sheet1!$B:$B,[1]Sheet1!$S:$S,0) -> 0 | Q1741: =_xlfn.XLOOKUP(B1741,[1]Sheet1!$B:$B,[1]Sheet1!$T:$T,0) -> 0 | R1741: =_xlfn.XLOOKUP(B1741,[1]Sheet1!$B:$B,[1]Sheet1!$U:$U,0) -> 0 | S1741: =_xlfn.XLOOKUP(B1741,[1]Sheet1!$B:$B,[1]Sheet1!$V:$V,0) -> 0 | T1741: =_xlfn.XLOOKUP(B1741,[1]Sheet1!$B:$B,[1]Sheet1!$W:$W,0) -> 0 | U1741: =_xlfn.XLOOKUP(B1741,[1]Sheet1!$B:$B,[1]Sheet1!$X:$X,0) -> 0 | V1741: =_xlfn.XLOOKUP(B1741,[1]Sheet1!$B:$B,[1]Sheet1!$Y:$Y,0) -> 0 | W1741: =SUM(K1741:V1741) -> 0 | X1741: 451.070402.4514000.1.491811.4510700.300105.000.000000.000000 | Y1741: Museum Shared Services | Z1741: Museums - Director’s Office | AA1741: 491811 - Heritage and cultural assets - Capital Expenditure | AB1741: 300105 - FA105-Capex Expense | AC1741: Chapter 3 | AD1741: 070402 - Museums development | AE1741: Museum Shared Services | AF1741: MSS OPEX Project Type | AG1741: 1317223 | AH1741: =_xlfn.XLOOKUP(B1741,[1]Sheet1!$B:$B,[1]Sheet1!$AB:$AB,0) -> 0

Sheet How to use
A1: The template is pre-filled with every project / task / expenditure type of the selected budget year, its full 10-segment GL combination and any cashflow amounts already saved — type the monthly amounts and upload the same file back.
A3: Budget year: 2026 | budget lines: 1739
A4: Keys (must not be edited): PROJECT, TASK, EXPENDITURE_TYPE.
A5: CF_TYPE = APPROVED or REVISED — copy a row and switch it to plan both.
A6: One column per accounting period (MM-YYYY): type the amount in the month cell.
A7: Blank month cells are ignored on upload; a typed 0 clears a saved amount.
A8: Columns after the months (GL_COMBINATION, SECTOR, ...) are reference only.

Sheet Details
N2: =SUBTOTAL(9,N4:N1366) -> 1574767 | O2: =SUBTOTAL(9,O4:O1366) -> 10563367 | P2: =SUBTOTAL(9,P4:P1366) -> 1.2557259e+09 | Q2: =SUBTOTAL(9,Q4:Q1366) -> 5.5583957e+08 | R2: =SUBTOTAL(9,R4:R1366) -> 4.4100864e+08 | S2: =SUBTOTAL(9,S4:S1366) -> 4.9972625e+08 | T2: =SUBTOTAL(9,T4:T1366) -> 2.5108327e+08 | U2: =SUBTOTAL(9,U4:U1366) -> 3.2774857e+08 | ... Z2: =SUBTOTAL(9,Z4:Z1366) -> 5.1401321e+09 | AB2: =SUBTOTAL(9,AB4:AB1366) -> 5.3650749e+09 | AC2: =SUBTOTAL(9,AC4:AC1366) -> 5.365563e+09 | AD2: =SUBTOTAL(9,AD4:AD1366) -> -488082.93 | AE2: =SUBTOTAL(9,AE4:AE1366) -> 5.3664863e+09 | AF2: =SUBTOTAL(9,AF4:AF1366) -> 1411332.9
B3: Com | C3: Sector | D3: Cost Center | E3: Department | F3: Project Number | G3: Project Name | H3: Task | I3: GL | J3: Future | K3: Chapter | L3: PBB | M3: Strategy type | N3: 46048 | O3: 46079 | P3: 46107 | Q3: 46138 | R3: 46168 | S3: 46199 | T3: 46229 | U3: 46260 | V3: 46291 | W3: 46321 | X3: 46352 | Y3: 46382 | Z3: Final Allocation with Revised CF | AB3: Revised CF after Budget Transfer | AC3: System Old Report | AD3: Diff. CF after budget transfer Vs System | AE3: Total Hany
B4: =D4&F4&H4&I4&J4 -> 45101954511000666Activation&Prog-N1422401200104 | C4: Arabic Language Centre | D4: 4510195 | E4: ALC - Arabic Language Centre (Central) | F4: 4511000666 | G4: ALC Executive Director's Office Operations | H4: Activation&Prog-N1 | I4: 422401 | J4: 200104 | K4: Opex | L4: 70101 | M4: Operational | N4: 0 | O4: 4460 | P4: 0 | Q4: 0 | R4: 0 | S4: 245540 | T4: 0 | U4: 0 | V4: 0 | W4: 0 | X4: 300000 | Y4: 450000 | Z4: =SUM(N4:Y4) -> 1000000 | AB4: 959000 | AC4: 959000 | AD4: 0 | AE4: =_xlfn.XLOOKUP(B4,'Projects Cashflow'!$B:$B,'Projects Cashflow'!$AG:$AG,0) -> 959000 | AF4: =AE4-AB4 -> 0
B5: =D5&F5&H5&I5&J5 -> 45101954511000666Mission & Travel-N1423821200104 | C5: Arabic Language Centre | D5: 4510195 | E5: ALC - Arabic Language Centre (Central) | F5: 4511000666 | G5: ALC Executive Director's Office Operations | H5: Mission & Travel-N1 | I5: 423821 | J5: 200104 | K5: Opex | L5: 70101 | M5: Operational | N5: 0 | O5: 233750 | P5: 0 | Q5: 161622 | R5: 153500 | S5: 77000 | T5: 0 | U5: 0 | V5: 0 | W5: 125000 | X5: 95000 | Y5: 0 | Z5: =SUM(N5:Y5) -> 845872 | AB5: 1245872 | AC5: 1245872 | AD5: 0 | AE5: =_xlfn.XLOOKUP(B5,'Projects Cashflow'!$B:$B,'Projects Cashflow'!$AG:$AG,0) -> 1245872 | AF5: =AE5-AB5 -> 0
B6: =D6&F6&H6&I6&J6 -> 45101954511000666Freelancers-N1424521200104 | C6: Arabic Language Centre | D6: 4510195 | E6: ALC - Arabic Language Centre (Central) | F6: 4511000666 | G6: ALC Executive Director's Office Operations | H6: Freelancers-N1 | I6: 424521 | J6: 200104 | K6: Opex | L6: 70101 | M6: Internal Strategic | N6: 0 | O6: 15000 | P6: 15000 | Q6: 30000 | R6: 15000 | S6: 15000 | T6: 0 | U6: 0 | V6: 0 | W6: 0 | X6: 0 | Y6: 0 | Z6: =SUM(N6:Y6) -> 90000 | AB6: 75500 | AC6: 75500 | AD6: 0 | AE6: =_xlfn.XLOOKUP(B6,'Projects Cashflow'!$B:$B,'Projects Cashflow'!$AG:$AG,0) -> 75500 | AF6: =AE6-AB6 -> 0
B7: =D7&F7&H7&I7&J7 -> 45101954511000892Freelancers-N2424521200104 | C7: Arabic Language Centre | D7: 4510195 | E7: ALC - Arabic Language Centre (Central) | F7: 4511000892 | G7: ALC Internal Communications | H7: Freelancers-N2 | I7: 424521 | J7: 200104 | K7: Opex | L7: 70101 | M7: Operational | N7: 0 | O7: 0 | P7: 15000 | Q7: 45000 | R7: 25000 | S7: 25000 | T7: 25000 | U7: 25000 | V7: 35000 | W7: 35000 | X7: 35000 | Y7: 35000 | Z7: =SUM(N7:Y7) -> 300000 | AB7: 315500 | AC7: 315500 | AD7: 0 | AE7: =_xlfn.XLOOKUP(B7,'Projects Cashflow'!$B:$B,'Projects Cashflow'!$AG:$AG,0) -> 315500 | AF7: =AE7-AB7 -> 0
B8: =D8&F8&H8&I8&J8 -> 45101954511000892Event Management-N2422401200104 | C8: Arabic Language Centre | D8: 4510195 | E8: ALC - Arabic Language Centre (Central) | F8: 4511000892 | G8: ALC Internal Communications | H8: Event Management-N2 | I8: 422401 | J8: 200104 | K8: Opex | L8: 70101 | M8: Operational | N8: 0 | O8: 0 | P8: 0 | Q8: 158938 | R8: 0 | S8: 0 | T8: 0 | U8: 8000 | V8: 0 | W8: 0 | X8: 7000 | Y8: 9000 | Z8: =SUM(N8:Y8) -> 182938 | AB8: 182938 | AC8: 182938 | AD8: 0 | AE8: =_xlfn.XLOOKUP(B8,'Projects Cashflow'!$B:$B,'Projects Cashflow'!$AG:$AG,0) -> 182938 | AF8: =AE8-AB8 -> 0
B9: =D9&F9&H9&I9&J9 -> 45101954511000892Edit & Copywrite-N2421115200104 | C9: Arabic Language Centre | D9: 4510195 | E9: ALC - Arabic Language Centre (Central) | F9: 4511000892 | G9: ALC Internal Communications | H9: Edit & Copywrite-N2 | I9: 421115 | J9: 200104 | K9: Opex | L9: 70704 | M9: Operational | N9: 0 | O9: 0 | P9: 0 | Q9: 68000 | R9: 4000 | S9: 4000 | T9: 4000 | U9: 4000 | V9: 4000 | W9: 4000 | X9: 4000 | Y9: 4000 | Z9: =SUM(N9:Y9) -> 100000 | AB9: 100000 | AC9: 100000 | AD9: 0 | AE9: =_xlfn.XLOOKUP(B9,'Projects Cashflow'!$B:$B,'Projects Cashflow'!$AG:$AG,0) -> 100000 | AF9: =AE9-AB9 -> 0
B10: =D10&F10&H10&I10&J10 -> 45101954511001251Event Management-N1422401200104 | C10: Arabic Language Centre | D10: 4510195 | E10: ALC - Arabic Language Centre (Central) | F10: 4511001251 | G10: Support Services Affairsq | H10: Event Management-N1 | I10: 422401 | J10: 200104 | K10: Opex | L10: 70701 | M10: Internal Strategic | N10: 0 | O10: 0 | P10: 0 | Q10: 63000 | R10: 0 | S10: 0 | T10: 0 | U10: 0 | V10: 0 | W10: 99000 | X10: 0 | Y10: 0 | Z10: =SUM(N10:Y10) -> 162000 | AB10: 212000 | AC10: 212000 | AD10: 0 | AE10: =_xlfn.XLOOKUP(B10,'Projects Cashflow'!$B:$B,'Projects Cashflow'!$AG:$AG,0) -> 212000 | AF10: =AE10-AB10 -> 0
B11: =D11&F11&H11&I11&J11 -> 45191964511000667CampaignProductn-N1422511200104 | C11: Arabic Language Centre | D11: 4519196 | E11: ALC- Marketing & Communications Department | F11: 4511000667 | G11: ALC Marketing | H11: CampaignProductn-N1 | I11: 422511 | J11: 200104 | K11: Opex | L11: 70705 | M11: Operational | N11: 0 | O11: 0 | P11: 0 | Q11: 18000 | R11: 100000 | S11: 0 | T11: 0 | U11: 0 | V11: 0 | W11: 0 | X11: 0 | Y11: 32000 | Z11: =SUM(N11:Y11) -> 150000 | AB11: 150000 | AC11: 150000 | AD11: 0 | AE11: =_xlfn.XLOOKUP(B11,'Projects Cashflow'!$B:$B,'Projects Cashflow'!$AG:$AG,0) -> 150000 | AF11: =AE11-AB11 -> 0
B12: =D12&F12&H12&I12&J12 -> 45191964511000685PR&MediaCoverage-N1424781200104 | C12: Arabic Language Centre | D12: 4519196 | E12: ALC- Marketing & Communications Department | F12: 4511000685 | G12: Corporate Communication Office Operations | H12: PR&MediaCoverage-N1 | I12: 424781 | J12: 200104 | K12: Opex | L12: 70705 | M12: Operational | N12: 0 | O12: 0 | P12: 0 | Q12: 298080 | R12: 74520 | S12: 74520 | T12: 74520 | U12: 74520 | V12: 74520 | W12: 74520 | X12: 74520 | Y12: 173880 | Z12: =SUM(N12:Y12) -> 993600 | AB12: 993600 | AC12: 993600 | AD12: 0 | AE12: =_xlfn.XLOOKUP(B12,'Projects Cashflow'!$B:$B,'Projects Cashflow'!$AG:$AG,0) -> 993600 | AF12: =AE12-AB12 -> 0
B13: =D13&F13&H13&I13&J13 -> 45191964511000695Photo & Video-N424221200104 | C13: Arabic Language Centre | D13: 4519196 | E13: ALC- Marketing & Communications Department | F13: 4511000695 | G13: Zayed Poetry Encyclopedia | H13: Photo & Video-N | I13: 424221 | J13: 200104 | K13: Opex | L13: 70704 | M13: Operational | N13: 0 | O13: 0 | P13: 0 | Q13: 0 | R13: 0 | S13: 285000 | T13: 0 | U13: 0 | V13: 0 | W13: 0 | X13: 0 | Y13: 0 | Z13: =SUM(N13:Y13) -> 285000 | AB13: 285000 | AC13: 285000 | AD13: 0 | AE13: =_xlfn.XLOOKUP(B13,'Projects Cashflow'!$B:$B,'Projects Cashflow'!$AG:$AG,0) -> 285000 | AF13: =AE13-AB13 -> 0
B14: =D14&F14&H14&I14&J14 -> 45191964511000729PR&MediaCoverage-N1424781200104 | C14: Arabic Language Centre | D14: 4519196 | E14: ALC- Marketing & Communications Department | F14: 4511000729 | G14: ABP- Al Dhafra Exhibition | H14: PR&MediaCoverage-N1 | I14: 424781 | J14: 200104 | K14: Opex | L14: 70704 | M14: Internal Strategic | N14: 0 | O14: 0 | P14: 0 | Q14: 115000 | R14: 0 | S14: 0 | T14: 0 | U14: 0 | V14: 0 | W14: 0 | X14: 0 | Y14: 0 | Z14: =SUM(N14:Y14) -> 115000 | AB14: 290000 | AC14: 290000 | AD14: 0 | AE14: =_xlfn.XLOOKUP(B14,'Projects Cashflow'!$B:$B,'Projects Cashflow'!$AG:$AG,0) -> 290000 | AF14: =AE14-AB14 -> 0
B15: =D15&F15&H15&I15&J15 -> 45191964511000730PR&MediaCoverage-N1424781200104 | C15: Arabic Language Centre | D15: 4519196 | E15: ALC- Marketing & Communications Department | F15: 4511000730 | G15: ABP- AlAin Exhibition | H15: PR&MediaCoverage-N1 | I15: 424781 | J15: 200104 | K15: Opex | L15: 70703 | M15: Internal Strategic | N15: 0 | O15: 0 | P15: 0 | Q15: 0 | R15: 0 | S15: 0 | T15: 0 | U15: 0 | V15: 0 | W15: 0 | X15: 625000 | Y15: 0 | Z15: =SUM(N15:Y15) -> 625000 | AB15: 625000 | AC15: 625000 | AD15: 0 | AE15: =_xlfn.XLOOKUP(B15,'Projects Cashflow'!$B:$B,'Projects Cashflow'!$AG:$AG,0) -> 625000 | AF15: =AE15-AB15 -> 0
... B18: =D18&F18&H18&I18&J18 -> 45191964511000769Offline Ads-N1422511200104 | C18: Arabic Language Centre | D18: 4519196 | E18: ALC- Marketing & Communications Department | F18: 4511000769 | G18: ADIBF - Abu Dhabi International Book Fair | H18: Offline Ads-N1 | I18: 422511 | J18: 200104 | K18: Opex | L18: 70704 | M18: Internal Strategic | N18: 0 | O18: 0 | P18: 0 | Q18: 250000 | R18: 250000 | S18: 0 | T18: 0 | U18: 0 | V18: 0 | W18: 0 | X18: 0 | Y18: 0 | Z18: =SUM(N18:Y18) -> 500000 | AB18: 500000 | AC18: 500000 | AD18: 0 | AE18: =_xlfn.XLOOKUP(B18,'Projects Cashflow'!$B:$B,'Projects Cashflow'!$AG:$AG,0) -> 500000 | AF18: =AE18-AB18 -> 0
B19: =D19&F19&H19&I19&J19 -> 45191964511000886SM Managnt E-E-N1422511200104 | C19: Arabic Language Centre | D19: 4519196 | E19: ALC- Marketing & Communications Department | F19: 4511000886 | G19: Digital Content Production | H19: SM Managnt E-E-N1 | I19: 422511 | J19: 200104 | K19: Opex | L19: 70705 | M19: Operational | N19: 0 | O19: 0 | P19: 736200 | R19: 736200 | S19: 736200 | T19: 368100 | U19: 368100 | V19: 368100 | W19: 368100 | X19: 368100 | Y19: 1840500 | Z19: =SUM(N19:Y19) -> 5889600 | AB19: 5889600 | AC19: 5889600 | AD19: 0 | AE19: =_xlfn.XLOOKUP(B19,'Projects Cashflow'!$B:$B,'Projects Cashflow'!$AG:$AG,0) -> 5889600 | AF19: =AE19-AB19 -> 0
B20: =D20&F20&H20&I20&J20 -> 45191964511000886Online Ads-N1422511200104 | C20: Arabic Language Centre | D20: 4519196 | E20: ALC- Marketing & Communications Department | F20: 4511000886 | G20: Digital Content Production | H20: Online Ads-N1 | I20: 422511 | J20: 200104 | K20: Opex | L20: 70705 | M20: Operational | N20: 0 | O20: 0 | P20: 0 | Q20: 500000 | R20: 0 | S20: 334748 | T20: 0 | U20: 0 | V20: 300000 | W20: 0 | X20: 0 | Y20: 510036 | Z20: =SUM(N20:Y20) -> 1644784 | AB20: 1930416 | AC20: 1930416 | AD20: 0 | AE20: =_xlfn.XLOOKUP(B20,'Projects Cashflow'!$B:$B,'Projects Cashflow'!$AG:$AG,0) -> 1930416 | AF20: =AE20-AB20 -> 0
B21: =D21&F21&H21&I21&J21 -> 45191964511000886SM Prodct&Develp-N1422511200104 | C21: Arabic Language Centre | D21: 4519196 | E21: ALC- Marketing & Communications Department | F21: 4511000886 | G21: Digital Content Production | H21: SM Prodct&Develp-N1 | I21: 422511 | J21: 200104 | K21: Opex | L21: 70705 | M21: Operational | N21: 0 | O21: 0 | P21: 0 | Q21: 0 | R21: 0 | S21: 0 | T21: 750000 | U21: 0 | V21: 0 | W21: 0 | X21: 0 | Y21: 0 | Z21: =SUM(N21:Y21) -> 750000 | AB21: 750000 | AC21: 750000 | AD21: 0 | AE21: =_xlfn.XLOOKUP(B21,'Projects Cashflow'!$B:$B,'Projects Cashflow'!$AG:$AG,0) -> 750000 | AF21: =AE21-AB21 -> 0
B22: =D22&F22&H22&I22&J22 -> 45191964511000886Photo & Video-N1424221200104 | C22: Arabic Language Centre | D22: 4519196 | E22: ALC- Marketing & Communications Department | F22: 4511000886 | G22: Digital Content Production | H22: Photo & Video-N1 | I22: 424221 | J22: 200104 | K22: Opex | L22: 70705 | M22: Operational | N22: 0 | O22: 0 | P22: 0 | Q22: 250000 | R22: 250000 | S22: 0 | T22: 0 | U22: 0 | V22: 0 | W22: 0 | X22: 0 | Y22: 0 | Z22: =SUM(N22:Y22) -> 500000 | AB22: 500000 | AC22: 500000 | AD22: 0 | AE22: =_xlfn.XLOOKUP(B22,'Projects Cashflow'!$B:$B,'Projects Cashflow'!$AG:$AG,0) -> 500000 | AF22: =AE22-AB22 -> 0
B23: =D23&F23&H23&I23&J23 -> 45191964511000887Freelancers-N1424521200104 | C23: Arabic Language Centre | D23: 4519196 | E23: ALC- Marketing & Communications Department | F23: 4511000887 | G23: Marketing & Communications | H23: Freelancers-N1 | I23: 424521 | J23: 200104 | K23: Opex | L23: 70705 | M23: Operational | N23: 0 | O23: 40000 | P23: 21333 | Q23: 41332 | R23: 40000 | S23: 58667 | T23: 58278 | U23: 58278 | V23: 58278 | W23: 58278 | X23: 58278 | Y23: 58278 | Z23: =SUM(N23:Y23) -> 551000 | AB23: 460500 | AC23: 460500 | AD23: 0 | AE23: =_xlfn.XLOOKUP(B23,'Projects Cashflow'!$B:$B,'Projects Cashflow'!$AG:$AG,0) -> 460500 | AF23: =AE23-AB23 -> 0
B24: =D24&F24&H24&I24&J24 -> 45191964511000887Mission & Travel-N1423821200104 | C24: Arabic Language Centre | D24: 4519196 | E24: ALC- Marketing & Communications Department | F24: 4511000887 | G24: Marketing & Communications | H24: Mission & Travel-N1 | I24: 423821 | J24: 200104 | K24: Opex | L24: 70705 | M24: Operational | N24: 0 | O24: 41500 | P24: 0 | Q24: 144000 | R24: 0 | S24: 0 | T24: 0 | U24: 0 | V24: 0 | W24: 0 | X24: 22500 | Y24: 177000 | Z24: =SUM(N24:Y24) -> 385000 | AB24: 385000 | AC24: 385000 | AD24: 0 | AE24: =_xlfn.XLOOKUP(B24,'Projects Cashflow'!$B:$B,'Projects Cashflow'!$AG:$AG,0) -> 385000 | AF24: =AE24-AB24 -> 0
B25: =D25&F25&H25&I25&J25 -> 45191964511000887E-E Ops and Prod-N1421125200104 | C25: Arabic Language Centre | D25: 4519196 | E25: ALC- Marketing & Communications Department | F25: 4511000887 | G25: Marketing & Communications | H25: E-E Ops and Prod-N1 | I25: 421125 | J25: 200104 | K25: Opex | L25: 70705 | M25: Internal Strategic | N25: 0 | O25: 0 | P25: 0 | Q25: 16000 | R25: 0 | S25: 16000 | T25: 0 | U25: 10000 | V25: 16000 | W25: 16000 | X25: 16000 | Y25: 10069 | Z25: =SUM(N25:Y25) -> 100069 | AB25: 100069 | AC25: 100069 | AD25: 0 | AE25: =_xlfn.XLOOKUP(B25,'Projects Cashflow'!$B:$B,'Projects Cashflow'!$AG:$AG,0) -> 100069 | AF25: =AE25-AB25 -> 0
B26: =D26&F26&H26&I26&J26 -> 45191964511000887Hospitality-N1424761200104 | C26: Arabic Language Centre | D26: 4519196 | E26: ALC- Marketing & Communications Department | F26: 4511000887 | G26: Marketing & Communications | H26: Hospitality-N1 | I26: 424761 | J26: 200104 | K26: Opex | L26: 70705 | M26: Operational | N26: 0 | O26: 61333 | P26: 0 | Q26: 8667 | R26: 0 | S26: 0 | T26: 0 | U26: 0 | V26: 0 | W26: 0 | X26: 30000 | Y26: 0 | Z26: =SUM(N26:Y26) -> 100000 | AB26: 100000 | AC26: 100000 | AD26: 0 | AE26: =_xlfn.XLOOKUP(B26,'Projects Cashflow'!$B:$B,'Projects Cashflow'!$AG:$AG,0) -> 100000 | AF26: =AE26-AB26 -> 0
B27: =D27&F27&H27&I27&J27 -> 45191964511000890Brand Management-N1422511200104 | C27: Arabic Language Centre | D27: 4519196 | E27: ALC- Marketing & Communications Department | F27: 4511000890 | G27: Marketing Operations | H27: Brand Management-N1 | I27: 422511 | J27: 200104 | K27: Opex | L27: 70705 | M27: Operational | N27: 0 | O27: 12555 | P27: 79147.5 | Q27: 15877.5 | R27: 37745 | S27: 25190 | T27: 20263 | U27: 20263 | V27: 20263 | W27: 20263 | X27: 20263 | Y27: 9000 | Z27: =SUM(N27:Y27) -> 280830 | AB27: 371330 | AC27: 371330 | AD27: 0 | AE27: =_xlfn.XLOOKUP(B27,'Projects Cashflow'!$B:$B,'Projects Cashflow'!$AG:$AG,0) -> 371330 | AF27: =AE27-AB27 -> 0
B28: =D28&F28&H28&I28&J28 -> 45191964511001500CampaignProductn-N422511200104 | C28: Arabic Language Centre | D28: 4519196 | E28: ALC- Marketing & Communications Department | F28: 4511001500 | G28: 101 Tales: Voices of Arabic Literature | H28: CampaignProductn-N | I28: 422511 | J28: 200104 | K28: Opex | L28: 70705 | M28: Operational | N28: 0 | O28: 0 | P28: 0 | Q28: 0 | R28: 0 | S28: 0 | T28: 500000 | U28: 0 | V28: 0 | W28: 0 | X28: 0 | Y28: 0 | Z28: =SUM(N28:Y28) -> 500000 | AB28: 500000 | AC28: 500000 | AD28: 0 | AE28: =_xlfn.XLOOKUP(B28,'Projects Cashflow'!$B:$B,'Projects Cashflow'!$AG:$AG,0) -> 500000 | AF28: =AE28-AB28 -> 0
B29: =D29&F29&H29&I29&J29 -> 45191974511000681Mission & Travel-N1423821200104 | C29: Arabic Language Centre | D29: 4519197 | E29: ALC- Arabic Language Education & Research Department | F29: 4511000681 | G29: AL Education & Research Operations | H29: Mission & Travel-N1 | I29: 423821 | J29: 200104 | K29: Opex | L29: 70701 | M29: Operational | N29: 0 | O29: 0 | P29: 0 | Q29: 0 | R29: 39000 | S29: 0 | T29: 0 | U29: 0 | V29: 0 | W29: 24000 | X29: 37000 | Y29: 0 | Z29: =SUM(N29:Y29) -> 100000 | AB29: 100000 | AC29: 100000 | AD29: 0 | AE29: =_xlfn.XLOOKUP(B29,'Projects Cashflow'!$B:$B,'Projects Cashflow'!$AG:$AG,0) -> 100000 | AF29: =AE29-AB29 -> 0
B30: =D30&F30&H30&I30&J30 -> 45191974511000727Sponsorship Fees-N1424811200104 | C30: Arabic Language Centre | D30: 4519197 | E30: ALC- Arabic Language Education & Research Department | F30: 4511000727 | G30: Arabic Language Proficiency Exam | H30: Sponsorship Fees-N1 | I30: 424811 | J30: 200104 | K30: Opex | L30: 70701 | M30: Operational | N30: 0 | O30: 0 | P30: 0 | Q30: 0 | R30: 0 | S30: 0 | T30: 0 | U30: 0 | V30: 2500000 | W30: 0 | X30: 0 | Y30: 0 | Z30: =SUM(N30:Y30) -> 2500000 | AB30: 2500000 | AC30: 2500000 | AD30: 0 | AE30: =_xlfn.XLOOKUP(B30,'Projects Cashflow'!$B:$B,'Projects Cashflow'!$AG:$AG,0) -> 2500000 | AF30: =AE30-AB30 -> 0
B31: =D31&F31&H31&I31&J31 -> 45191974511000728Freelancers-N424521200104 | C31: Arabic Language Centre | D31: 4519197 | E31: ALC- Arabic Language Education & Research Department | F31: 4511000728 | G31: Moderna Arabic lexicon | H31: Freelancers-N | I31: 424521 | J31: 200104 | K31: Opex | L31: 70704 | M31: Operational | N31: 0 | O31: 36500 | P31: 36500 | Q31: 73000 | R31: 36500 | S31: 36500 | T31: 0 | U31: 0 | V31: 0 | W31: 0 | X31: 0 | Y31: 0 | Z31: =SUM(N31:Y31) -> 219000 | AB31: 219000 | AC31: 219000 | AD31: 0 | AE31: =_xlfn.XLOOKUP(B31,'Projects Cashflow'!$B:$B,'Projects Cashflow'!$AG:$AG,0) -> 219000 | AF31: =AE31-AB31 -> 0
... B87: =D87&F87&H87&I87&J87 -> 45192004511000769Activation&Prog-N2422401200104 | C87: Arabic Language Centre | D87: 4519200 | E87: ALC- Bookfairs & Events Department | F87: 4511000769 | G87: ADIBF - Abu Dhabi International Book Fair | H87: Activation&Prog-N2 | I87: 422401 | J87: 200104 | K87: Opex | L87: 70703 | M87: Internal Strategic | N87: 0 | O87: 0 | P87: 0 | Q87: 0 | R87: 0 | S87: 0 | T87: 0 | U87: 0 | V87: 0 | W87: 1534890 | X87: 0 | Y87: 0 | Z87: =SUM(N87:Y87) -> 1534890 | AB87: 2428412 | AC87: 2428412 | AD87: 0 | AE87: =_xlfn.XLOOKUP(B87,'Projects Cashflow'!$B:$B,'Projects Cashflow'!$AG:$AG,0) -> 2428412 | AF87: =AE87-AB87 -> 0
B88: =D88&F88&H88&I88&J88 -> 45157004511000860Co-Invest Events-N422401200104 | C88: Tourism | D88: 4515700 | E88: DCT-Destination Management Department | F88: 4511000860 | G88: Al Ain Destination Strategy | H88: Co-Invest Events-N | I88: 422401 | J88: 200104 | K88: Opex | L88: 70501 | M88: Operational | Z88: =SUM(N88:Y88) -> 0 | AB88: 10000000 | AC88: 10000000 | AD88: 0 | AE88: =_xlfn.XLOOKUP(B88,'Projects Cashflow'!$B:$B,'Projects Cashflow'!$AG:$AG,0) -> 10000000 | AF88: =AE88-AB88 -> 0
B89: =D89&F89&H89&I89&J89 -> 45192004511000883Mission & Travel-N1423821200104 | C89: Arabic Language Centre | D89: 4519200 | E89: ALC- Bookfairs & Events Department | F89: 4511000883 | G89: Bookfairs & Events Operations | H89: Mission & Travel-N1 | I89: 423821 | J89: 200104 | K89: Opex | L89: 70703 | M89: Operational | N89: 0 | O89: 182000 | P89: 0 | Q89: 18000 | R89: 50000 | S89: 50000 | T89: 50000 | U89: 50000 | V89: 50000 | W89: 150000 | X89: 25000 | Y89: 50000 | Z89: =SUM(N89:Y89) -> 675000 | AB89: 649000 | AC89: 675000 | AD89: -26000 | AE89: =_xlfn.XLOOKUP(B89,'Projects Cashflow'!$B:$B,'Projects Cashflow'!$AG:$AG,0) -> 675000 | AF89: =AE89-AB89 -> 26000
B90: =D90&F90&H90&I90&J90 -> 45192004511000883Freelancers-N1424521200104 | C90: Arabic Language Centre | D90: 4519200 | E90: ALC- Bookfairs & Events Department | F90: 4511000883 | G90: Bookfairs & Events Operations | H90: Freelancers-N1 | I90: 424521 | J90: 200104 | K90: Opex | L90: 70704 | M90: Operational | N90: 0 | O90: 36000 | P90: 0 | Q90: 36000 | R90: 18000 | S90: 18000 | T90: 18000 | U90: 18000 | V90: 18000 | W90: 18000 | X90: 18000 | Y90: 18000 | Z90: =SUM(N90:Y90) -> 216000 | AB90: 216000 | AC90: 216000 | AD90: 0 | AE90: =_xlfn.XLOOKUP(B90,'Projects Cashflow'!$B:$B,'Projects Cashflow'!$AG:$AG,0) -> 216000 | AF90: =AE90-AB90 -> 0
B91: =D91&F91&H91&I91&J91 -> 45192014511000676Awards & Prizes-N2424231200104 | C91: Arabic Language Centre | D91: 4519201 | E91: ALC- Literature Awards Department | F91: 4511000676 | G91: ABP- SZBA | H91: Awards & Prizes-N2 | I91: 424231 | J91: 200104 | K91: Opex | L91: 70703 | M91: Internal Strategic | N91: 0 | O91: 0 | P91: 0 | Q91: 0 | R91: 0 | S91: 0 | T91: 500000 | U91: 5250000 | V91: 1000000 | W91: 0 | X91: 750000 | Y91: 0 | Z91: =SUM(N91:Y91) -> 7500000 | AB91: 7500000 | AC91: 7500000 | AD91: 0 | AE91: =_xlfn.XLOOKUP(B91,'Projects Cashflow'!$B:$B,'Projects Cashflow'!$AG:$AG,0) -> 7500000 | AF91: =AE91-AB91 -> 0
B92: =D92&F92&H92&I92&J92 -> 45192014511000676Event Management-N2422401200104 | C92: Arabic Language Centre | D92: 4519201 | E92: ALC- Literature Awards Department | F92: 4511000676 | G92: ABP- SZBA | H92: Event Management-N2 | I92: 422401 | J92: 200104 | K92: Opex | L92: 70703 | M92: Internal Strategic | N92: 0 | O92: 0 | P92: 0 | Q92: 0 | R92: 0 | S92: 0 | T92: 0 | U92: 0 | V92: 4400000 | W92: 0 | X92: 0 | Y92: 0 | Z92: =SUM(N92:Y92) -> 4400000 | AB92: 4400000 | AC92: 4400000 | AD92: 0 | AE92: =_xlfn.XLOOKUP(B92,'Projects Cashflow'!$B:$B,'Projects Cashflow'!$AG:$AG,0) -> 4400000 | AF92: =AE92-AB92 -> 0
B93: =D93&F93&H93&I93&J93 -> 45192014511000676PR&MediaCoverage-N2424781200104 | C93: Arabic Language Centre | D93: 4519201 | E93: ALC- Literature Awards Department | F93: 4511000676 | G93: ABP- SZBA | H93: PR&MediaCoverage-N2 | I93: 424781 | J93: 200104 | K93: Opex | L93: 70703 | M93: Internal Strategic | N93: 0 | O93: 0 | P93: 0 | Q93: 582000 | R93: 0 | S93: 0 | T93: 582000 | U93: 117500 | V93: 0 | W93: 0 | X93: 0 | Y93: 1000000 | Z93: =SUM(N93:Y93) -> 2281500 | AB93: 2281500 | AC93: 2281500 | AD93: 0 | AE93: =_xlfn.XLOOKUP(B93,'Projects Cashflow'!$B:$B,'Projects Cashflow'!$AG:$AG,0) -> 2281500 | AF93: =AE93-AB93 -> 0
B94: =D94&F94&H94&I94&J94 -> 45192014511000676Committee Member-N2421115200104 | C94: Arabic Language Centre | D94: 4519201 | E94: ALC- Literature Awards Department | F94: 4511000676 | G94: ABP- SZBA | H94: Committee Member-N2 | I94: 421115 | J94: 200104 | K94: Opex | L94: 70702 | M94: Internal Strategic | N94: 0 | O94: 0 | P94: 550000 | Q94: 0 | R94: 0 | S94: 0 | T94: 0 | U94: 275000 | V94: 635000 | W94: 460000 | X94: 0 | Y94: 0 | Z94: =SUM(N94:Y94) -> 1920000 | AB94: 1920000 | AC94: 1920000 | AD94: 0 | AE94: =_xlfn.XLOOKUP(B94,'Projects Cashflow'!$B:$B,'Projects Cashflow'!$AG:$AG,0) -> 1920000 | AF94: =AE94-AB94 -> 0
B95: =D95&F95&H95&I95&J95 -> 45192014511000676Hospitality-N2424761200104 | C95: Arabic Language Centre | D95: 4519201 | E95: ALC- Literature Awards Department | F95: 4511000676 | G95: ABP- SZBA | H95: Hospitality-N2 | I95: 424761 | J95: 200104 | K95: Opex | L95: 70703 | M95: Internal Strategic | N95: 0 | O95: 0 | P95: 0 | Q95: 200000 | R95: 0 | S95: 0 | T95: 0 | U95: 0 | V95: 0 | W95: 433000 | X95: 0 | Y95: 0 | Z95: =SUM(N95:Y95) -> 633000 | AB95: 633000 | AC95: 633000 | AD95: 0 | AE95: =_xlfn.XLOOKUP(B95,'Projects Cashflow'!$B:$B,'Projects Cashflow'!$AG:$AG,0) -> 633000 | AF95: =AE95-AB95 -> 0
B96: =D96&F96&H96&I96&J96 -> 45192014511000676TranslationGrant-N2424701200104 | C96: Arabic Language Centre | D96: 4519201 | E96: ALC- Literature Awards Department | F96: 4511000676 | G96: ABP- SZBA | H96: TranslationGrant-N2 | I96: 424701 | J96: 200104 | K96: Opex | L96: 70702 | M96: Operational | N96: 0 | O96: 0 | P96: 0 | Q96: 75000 | R96: 50000 | S96: 75000 | T96: 0 | U96: 75000 | V96: 75000 | W96: 20000 | X96: 0 | Y96: 0 | Z96: =SUM(N96:Y96) -> 370000 | AB96: 370000 | AC96: 370000 | AD96: 0 | AE96: =_xlfn.XLOOKUP(B96,'Projects Cashflow'!$B:$B,'Projects Cashflow'!$AG:$AG,0) -> 370000 | AF96: =AE96-AB96 -> 0
B97: =D97&F97&H97&I97&J97 -> 45192014511000676Prizes & Comps-N2424231200104 | C97: Arabic Language Centre | D97: 4519201 | E97: ALC- Literature Awards Department | F97: 4511000676 | G97: ABP- SZBA | H97: Prizes & Comps-N2 | I97: 424231 | J97: 200104 | K97: Opex | L97: 70703 | M97: Internal Strategic | N97: 0 | O97: 0 | P97: 0 | Q97: 20000 | R97: 0 | S97: 0 | T97: 130000 | U97: 0 | V97: 0 | W97: 0 | X97: 0 | Y97: 0 | Z97: =SUM(N97:Y97) -> 150000 | AB97: 150000 | AC97: 150000 | AD97: 0 | AE97: =_xlfn.XLOOKUP(B97,'Projects Cashflow'!$B:$B,'Projects Cashflow'!$AG:$AG,0) -> 150000 | AF97: =AE97-AB97 -> 0
B98: =D98&F98&H98&I98&J98 -> 45192014511000676Gen Logistics-N2424671200104 | C98: Arabic Language Centre | D98: 4519201 | E98: ALC- Literature Awards Department | F98: 4511000676 | G98: ABP- SZBA | H98: Gen Logistics-N2 | I98: 424671 | J98: 200104 | K98: Opex | L98: 70703 | M98: Internal Strategic | N98: 0 | O98: 0 | P98: 0 | Q98: 0 | R98: 0 | S98: 0 | T98: 0 | U98: 0 | V98: 10000 | W98: 0 | X98: 10000 | Y98: 5000 | Z98: =SUM(N98:Y98) -> 25000 | AB98: 25000 | AC98: 25000 | AD98: 0 | AE98: =_xlfn.XLOOKUP(B98,'Projects Cashflow'!$B:$B,'Projects Cashflow'!$AG:$AG,0) -> 25000 | AF98: =AE98-AB98 -> 0
B99: =D99&F99&H99&I99&J99 -> 45192014511000731Sponsorship Fees-N2424811200104 | C99: Arabic Language Centre | D99: 4519201 | E99: ALC- Literature Awards Department | F99: 4511000731 | G99: IPAF Award | H99: Sponsorship Fees-N2 | I99: 424811 | J99: 200104 | K99: Opex | L99: 70704 | M99: Operational | N99: 0 | O99: 0 | P99: 0 | Q99: 0 | R99: 0 | S99: 0 | T99: 1652940 | U99: 0 | V99: 0 | W99: 0 | X99: 0 | Y99: 0 | Z99: =SUM(N99:Y99) -> 1652940 | AB99: 1652940 | AC99: 1652940 | AD99: 0 | AE99: =_xlfn.XLOOKUP(B99,'Projects Cashflow'!$B:$B,'Projects Cashflow'!$AG:$AG,0) -> 1652940 | AF99: =AE99-AB99 -> 0
B100: =D100&F100&H100&I100&J100 -> 45192014511000880Awards & Prizes-N2424231200104 | C100: Arabic Language Centre | D100: 4519201 | E100: ALC- Literature Awards Department | F100: 4511000880 | G100: KAJ - Kanz Al Jeel | H100: Awards & Prizes-N2 | I100: 424231 | J100: 200104 | K100: Opex | L100: 70703 | M100: Internal Strategic | N100: 0 | O100: 0 | P100: 0 | Q100: 0 | R100: 0 | S100: 0 | T100: 0 | U100: 0 | V100: 0 | W100: 0 | X100: 750000 | Y100: 750000 | Z100: =SUM(N100:Y100) -> 1500000 | AB100: 1500000 | AC100: 1500000 | AD100: 0 | AE100: =_xlfn.XLOOKUP(B100,'Projects Cashflow'!$B:$B,'Projects Cashflow'!$AG:$AG,0) -> 1500000 | AF100: =AE100-AB100 -> 0
... B115: =D115&F115&H115&I115&J115 -> 45192024511000675Mission & Travel-N2423821200104 | C115: Arabic Language Centre | D115: 4519202 | E115: ALC- Specialized Library Department | F115: 4511000675 | G115: ABP- QAW | H115: Mission & Travel-N2 | I115: 423821 | J115: 200104 | K115: Opex | L115: 70702 | M115: Operational | N115: 0 | O115: 0 | P115: 130700 | Q115: 0 | R115: 0 | S115: 67200 | T115: 0 | U115: 40000 | V115: 0 | W115: 0 | X115: 122100 | Y115: 0 | Z115: =SUM(N115:Y115) -> 360000 | AB115: 308000 | AC115: 308000 | AD115: 0 | AE115: =_xlfn.XLOOKUP(B115,'Projects Cashflow'!$B:$B,'Projects Cashflow'!$AG:$AG,0) -> 308000 | AF115: =AE115-AB115 -> 0
B116: =D116&F116&H116&I116&J116 -> 45192024511000675FreelancerN1424521200104 | C116: Arabic Language Centre | D116: 4519202 | E116: ALC- Specialized Library Department | F116: 4511000675 | G116: ABP- QAW | H116: FreelancerN1 | I116: 424521 | J116: 200104 | K116: Opex | L116: 70704 | M116: Operational | Z116: =SUM(N116:Y116) -> 0 | AB116: 70000 | AC116: 70000 | AD116: 0 | AE116: =_xlfn.XLOOKUP(B116,'Projects Cashflow'!$B:$B,'Projects Cashflow'!$AG:$AG,0) -> 70000 | AF116: =AE116-AB116 -> 0
B117: =D117&F117&H117&I117&J117 -> 45192024511000675Hospitality-N2424761200104 | C117: Arabic Language Centre | D117: 4519202 | E117: ALC- Specialized Library Department | F117: 4511000675 | G117: ABP- QAW | H117: Hospitality-N2 | I117: 424761 | J117: 200104 | K117: Opex | L117: 70702 | M117: Operational | N117: 0 | O117: 0 | P117: 0 | Q117: 0 | R117: 0 | S117: 50000 | T117: 0 | U117: 15000 | V117: 0 | W117: 69718 | X117: 20000 | Y117: 34000 | Z117: =SUM(N117:Y117) -> 188718 | AB117: 188718 | AC117: 188718 | AD117: 0 | AE117: =_xlfn.XLOOKUP(B117,'Projects Cashflow'!$B:$B,'Projects Cashflow'!$AG:$AG,0) -> 188718 | AF117: =AE117-AB117 -> 0
B118: =D118&F118&H118&I118&J118 -> 45192024511000675Photo & Video-N2424221200104 | C118: Arabic Language Centre | D118: 4519202 | E118: ALC- Specialized Library Department | F118: 4511000675 | G118: ABP- QAW | H118: Photo & Video-N2 | I118: 424221 | J118: 200104 | K118: Opex | L118: 70703 | M118: Operational | N118: 0 | O118: 0 | P118: 0 | Q118: 0 | R118: 0 | S118: 0 | T118: 0 | U118: 50000 | V118: 0 | W118: 0 | X118: 0 | Y118: 0 | Z118: =SUM(N118:Y118) -> 50000 | AB118: 50000 | AC118: 50000 | AD118: 0 | AE118: =_xlfn.XLOOKUP(B118,'Projects Cashflow'!$B:$B,'Projects Cashflow'!$AG:$AG,0) -> 50000 | AF118: =AE118-AB118 -> 0
B119: =D119&F119&H119&I119&J119 -> 45192034511000687Committee Member-N2421115200104 | C119: Arabic Language Centre | D119: 4519203 | E119: ALC- Strategic Planning Office | F119: 4511000687 | G119: Expert Linguistics and Academics Committee Honorariums | H119: Committee Member-N2 | I119: 421115 | J119: 200104 | K119: Opex | L119: 70701 | M119: Operational | N119: 0 | O119: 0 | P119: 0 | Q119: 0 | R119: 0 | S119: 0 | T119: 0 | U119: 0 | V119: 0 | W119: 0 | X119: 1000000 | Y119: 0 | Z119: =SUM(N119:Y119) -> 1000000 | AB119: 0 | AC119: 0 | AD119: 0 | AE119: =_xlfn.XLOOKUP(B119,'Projects Cashflow'!$B:$B,'Projects Cashflow'!$AG:$AG,0) -> 0 | AF119: =AE119-AB119 -> 0
B120: =D120&F120&H120&I120&J120 -> 45192034511000692Strategy Advice-N2421123200104 | C120: Arabic Language Centre | D120: 4519203 | E120: ALC- Strategic Planning Office | F120: 4511000692 | G120: Strategic Planning Operations | H120: Strategy Advice-N2 | I120: 421123 | J120: 200104 | K120: Opex | L120: 70701 | M120: Operational | N120: 0 | O120: 0 | P120: 0 | Q120: 1285999.3 | R120: 0 | S120: 0 | T120: 1285999.3 | U120: 0 | V120: 0 | W120: 1285999.3 | X120: 0 | Y120: 0 | Z120: =SUM(N120:Y120) -> 3857998 | AB120: 4005998 | AC120: 4005998 | AD120: 0 | AE120: =_xlfn.XLOOKUP(B120,'Projects Cashflow'!$B:$B,'Projects Cashflow'!$AG:$AG,0) -> 4005998 | AF120: =AE120-AB120 -> 0
B121: =D121&F121&H121&I121&J121 -> 45192034511000692Market Research-N2423411200104 | C121: Arabic Language Centre | D121: 4519203 | E121: ALC- Strategic Planning Office | F121: 4511000692 | G121: Strategic Planning Operations | H121: Market Research-N2 | I121: 423411 | J121: 200104 | K121: Opex | L121: 70701 | M121: Operational | N121: 0 | O121: 0 | P121: 0 | Q121: 491163 | R121: 0 | S121: 100000 | T121: 72091 | U121: 200000 | V121: 293373 | W121: 0 | X121: 0 | Y121: 293373 | Z121: =SUM(N121:Y121) -> 1450000 | AB121: 1450000 | AC121: 1450000 | AD121: 0 | AE121: =_xlfn.XLOOKUP(B121,'Projects Cashflow'!$B:$B,'Projects Cashflow'!$AG:$AG,0) -> 1450000 | AF121: =AE121-AB121 -> 0
B122: =D122&F122&H122&I122&J122 -> 45192034511000692Freelancers-N2424521200104 | C122: Arabic Language Centre | D122: 4519203 | E122: ALC- Strategic Planning Office | F122: 4511000692 | G122: Strategic Planning Operations | H122: Freelancers-N2 | I122: 424521 | J122: 200104 | K122: Opex | L122: 70701 | M122: Operational | N122: 0 | O122: 50000 | P122: 50000 | Q122: 100000 | R122: 50000 | S122: 50000 | T122: 50000 | U122: 50000 | V122: 49000 | W122: 40000 | X122: 40000 | Y122: 0 | Z122: =SUM(N122:Y122) -> 529000 | AB122: 579000 | AC122: 579000 | AD122: 0 | AE122: =_xlfn.XLOOKUP(B122,'Projects Cashflow'!$B:$B,'Projects Cashflow'!$AG:$AG,0) -> 579000 | AF122: =AE122-AB122 -> 0
B123: =D123&F123&H123&I123&J123 -> 45192034511000692Translation-N2424701200104 | C123: Arabic Language Centre | D123: 4519203 | E123: ALC- Strategic Planning Office | F123: 4511000692 | G123: Strategic Planning Operations | H123: Translation-N2 | I123: 424701 | J123: 200104 | K123: Opex | L123: 70701 | M123: Operational | N123: 0 | O123: 0 | P123: 0 | Q123: 116500 | R123: 0 | S123: 0 | T123: 14000 | U123: 0 | V123: 100000 | W123: 90000 | X123: 0 | Y123: 179500 | Z123: =SUM(N123:Y123) -> 500000 | AB123: 500000 | AC123: 500000 | AD123: 0 | AE123: =_xlfn.XLOOKUP(B123,'Projects Cashflow'!$B:$B,'Projects Cashflow'!$AG:$AG,0) -> 500000 | AF123: =AE123-AB123 -> 0
B124: =D124&F124&H124&I124&J124 -> 45192034511000692Mission & Travel-N2423821200104 | C124: Arabic Language Centre | D124: 4519203 | E124: ALC- Strategic Planning Office | F124: 4511000692 | G124: Strategic Planning Operations | H124: Mission & Travel-N2 | I124: 423821 | J124: 200104 | K124: Opex | L124: 70701 | M124: Operational | N124: 0 | O124: 4000 | P124: 0 | Q124: 46000 | R124: 0 | S124: 0 | T124: 0 | U124: 0 | V124: 0 | W124: 50000 | X124: 0 | Y124: 0 | Z124: =SUM(N124:Y124) -> 100000 | AB124: 160000 | AC124: 160000 | AD124: 0 | AE124: =_xlfn.XLOOKUP(B124,'Projects Cashflow'!$B:$B,'Projects Cashflow'!$AG:$AG,0) -> 160000 | AF124: =AE124-AB124 -> 0
B125: =D125&F125&H125&I125&J125 -> 45192034511000692Hospitality-N2424761200104 | C125: Arabic Language Centre | D125: 4519203 | E125: ALC- Strategic Planning Office | F125: 4511000692 | G125: Strategic Planning Operations | H125: Hospitality-N2 | I125: 424761 | J125: 200104 | K125: Opex | L125: 70701 | M125: Operational | N125: 0 | O125: 0 | P125: 0 | Q125: 10000 | R125: 0 | S125: 10000 | T125: 0 | U125: 10000 | V125: 20000 | W125: 5000 | X125: 10000 | Y125: 10000 | Z125: =SUM(N125:Y125) -> 75000 | AB125: 75000 | AC125: 75000 | AD125: 0 | AE125: =_xlfn.XLOOKUP(B125,'Projects Cashflow'!$B:$B,'Projects Cashflow'!$AG:$AG,0) -> 75000 | AF125: =AE125-AB125 -> 0
B126: =D126&F126&H126&I126&J126 -> 45192034511000881Event Management-N2422401200104 | C126: Arabic Language Centre | D126: 4519203 | E126: ALC- Strategic Planning Office | F126: 4511000881 | G126: International Congress (ICP) | H126: Event Management-N2 | I126: 422401 | J126: 200104 | K126: Opex | L126: 70704 | M126: Operational | N126: 0 | O126: 0 | P126: 0 | Q126: 750000 | R126: 0 | S126: 0 | T126: 0 | U126: 1500000 | V126: 2750000 | W126: 0 | X126: 0 | Y126: 0 | Z126: =SUM(N126:Y126) -> 5000000 | AB126: 5000000 | AC126: 5000000 | AD126: 0 | AE126: =_xlfn.XLOOKUP(B126,'Projects Cashflow'!$B:$B,'Projects Cashflow'!$AG:$AG,0) -> 5000000 | AF126: =AE126-AB126 -> 0
B127: =D127&F127&H127&I127&J127 -> 45192034511000881Hospitality-N2424761200104 | C127: Arabic Language Centre | D127: 4519203 | E127: ALC- Strategic Planning Office | F127: 4511000881 | G127: International Congress (ICP) | H127: Hospitality-N2 | I127: 424761 | J127: 200104 | K127: Opex | L127: 70704 | M127: Operational | N127: 0 | O127: 0 | P127: 0 | Q127: 0 | R127: 0 | S127: 0 | T127: 0 | U127: 0 | V127: 200000 | W127: 610373 | X127: 0 | Y127: 0 | Z127: =SUM(N127:Y127) -> 810373 | AB127: 810373 | AC127: 810373 | AD127: 0 | AE127: =_xlfn.XLOOKUP(B127,'Projects Cashflow'!$B:$B,'Projects Cashflow'!$AG:$AG,0) -> 810373 | AF127: =AE127-AB127 -> 0
B128: =D128&F128&H128&I128&J128 -> 45192034511000881Venue&Room Rent-N2422401200104 | C128: Arabic Language Centre | D128: 4519203 | E128: ALC- Strategic Planning Office | F128: 4511000881 | G128: International Congress (ICP) | H128: Venue&Room Rent-N2 | I128: 422401 | J128: 200104 | K128: Opex | L128: 70704 | M128: Operational | N128: 0 | O128: 0 | P128: 0 | Q128: 377816 | R128: 0 | S128: 0 | T128: 0 | U128: 0 | V128: 377816 | W128: 0 | X128: 0 | Y128: 0 | Z128: =SUM(N128:Y128) -> 755632 | AB128: 500000 | AC128: 500000 | AD128: 0 | AE128: =_xlfn.XLOOKUP(B128,'Projects Cashflow'!$B:$B,'Projects Cashflow'!$AG:$AG,0) -> 500000 | AF128: =AE128-AB128 -> 0
B129: =D129&F129&H129&I129&J129 -> 45192034511000881Media Mgmnt &Buy-N422511200104 | C129: Arabic Language Centre | D129: 4519203 | E129: ALC- Strategic Planning Office | F129: 4511000881 | G129: International Congress (ICP) | H129: Media Mgmnt &Buy-N | I129: 422511 | J129: 200104 | K129: Opex | L129: 70704 | M129: Operational | N129: 0 | O129: 0 | P129: 0 | Q129: 100000 | R129: 0 | S129: 0 | T129: 192887 | U129: 0 | V129: 200000 | W129: 0 | X129: 0 | Y129: 0 | Z129: =SUM(N129:Y129) -> 492887 | AB129: 492887 | AC129: 492887 | AD129: 0 | AE129: =_xlfn.XLOOKUP(B129,'Projects Cashflow'!$B:$B,'Projects Cashflow'!$AG:$AG,0) -> 492887 | AF129: =AE129-AB129 -> 0
B130: =D130&F130&H130&I130&J130 -> 45192034511000881Freelancers-N424521200104 | C130: Arabic Language Centre | D130: 4519203 | E130: ALC- Strategic Planning Office | F130: 4511000881 | G130: International Congress (ICP) | H130: Freelancers-N | I130: 424521 | J130: 200104 | K130: Opex | L130: 70704 | M130: Operational | Z130: =SUM(N130:Y130) -> 0 | AB130: 212000 | AC130: 212000 | AD130: 0 | AE130: =_xlfn.XLOOKUP(B130,'Projects Cashflow'!$B:$B,'Projects Cashflow'!$AG:$AG,0) -> 212000 | AF130: =AE130-AB130 -> 0
B131: =D131&F131&H131&I131&J131 -> 45192034511000881Talent Mgmnt-N2422401200104 | C131: Arabic Language Centre | D131: 4519203 | E131: ALC- Strategic Planning Office | F131: 4511000881 | G131: International Congress (ICP) | H131: Talent Mgmnt-N2 | I131: 422401 | J131: 200104 | K131: Opex | L131: 70704 | M131: Operational | N131: 0 | O131: 0 | P131: 0 | Q131: 0 | R131: 0 | S131: 0 | T131: 0 | U131: 0 | V131: 386192 | W131: 0 | X131: 0 | Y131: 0 | Z131: =SUM(N131:Y131) -> 386192 | AB131: 386192 | AC131: 386192 | AD131: 0 | AE131: =_xlfn.XLOOKUP(B131,'Projects Cashflow'!$B:$B,'Projects Cashflow'!$AG:$AG,0) -> 386192 | AF131: =AE131-AB131 -> 0
B132: =D132&F132&H132&I132&J132 -> 45192034511000881Event Consumable-N2421125200104 | C132: Arabic Language Centre | D132: 4519203 | E132: ALC- Strategic Planning Office | F132: 4511000881 | G132: International Congress (ICP) | H132: Event Consumable-N2 | I132: 421125 | J132: 200104 | K132: Opex | L132: 70704 | M132: Operational | N132: 0 | O132: 0 | P132: 0 | Q132: 75000 | R132: 0 | S132: 0 | T132: 0 | U132: 25000 | V132: 27729 | W132: 0 | X132: 0 | Y132: 0 | Z132: =SUM(N132:Y132) -> 127729 | AB132: 16729 | AC132: 16729 | AD132: 0 | AE132: =_xlfn.XLOOKUP(B132,'Projects Cashflow'!$B:$B,'Projects Cashflow'!$AG:$AG,0) -> 16729 | AF132: =AE132-AB132 -> 0
B133: =D133&F133&H133&I133&J133 -> 45192034511001179Design & Build-N2424221200104 | C133: Arabic Language Centre | D133: 4519203 | E133: ALC- Strategic Planning Office | F133: 4511001179 | G133: Arabian Days | H133: Design & Build-N2 | I133: 424221 | J133: 200104 | K133: Opex | L133: 70704 | M133: Internal Strategic | N133: 0 | O133: 0 | P133: 0 | Q133: 995000 | R133: 0 | S133: 0 | T133: 0 | U133: 0 | V133: 0 | W133: 1005000 | X133: 2191498.5 | Y133: 2191498.5 | Z133: =SUM(N133:Y133) -> 6382997 | AB133: 6382997 | AC133: 6382997 | AD133: 0 | AE133: =_xlfn.XLOOKUP(B133,'Projects Cashflow'!$B:$B,'Projects Cashflow'!$AG:$AG,0) -> 6382997 | AF133: =AE133-AB133 -> 0
B134: =D134&F134&H134&I134&J134 -> 45192034511001179Activation&Prog-N2422401200104 | C134: Arabic Language Centre | D134: 4519203 | E134: ALC- Strategic Planning Office | F134: 4511001179 | G134: Arabian Days | H134: Activation&Prog-N2 | I134: 422401 | J134: 200104 | K134: Opex | L134: 70704 | M134: Internal Strategic | N134: 0 | O134: 0 | P134: 0 | Q134: 0 | R134: 0 | S134: 0 | T134: 0 | U134: 0 | V134: 0 | W134: 2677458 | X134: 2677458 | Y134: 0 | Z134: =SUM(N134:Y134) -> 5354916 | AB134: 5354916 | AC134: 5354916 | AD134: 0 | AE134: =_xlfn.XLOOKUP(B134,'Projects Cashflow'!$B:$B,'Projects Cashflow'!$AG:$AG,0) -> 5354916 | AF134: =AE134-AB134 -> 0
B135: =D135&F135&H135&I135&J135 -> 45192034511001179Media Mgmnt &Buy-N2422511200104 | C135: Arabic Language Centre | D135: 4519203 | E135: ALC- Strategic Planning Office | F135: 4511001179 | G135: Arabian Days | H135: Media Mgmnt &Buy-N2 | I135: 422511 | J135: 200104 | K135: Opex | L135: 70704 | M135: Internal Strategic | N135: 0 | O135: 0 | P135: 0 | Q135: 0 | R135: 0 | S135: 0 | T135: 0 | U135: 0 | V135: 0 | W135: 0 | X135: 3296222 | Y135: 0 | Z135: =SUM(N135:Y135) -> 3296222 | AB135: 3296222 | AC135: 3296222 | AD135: 0 | AE135: =_xlfn.XLOOKUP(B135,'Projects Cashflow'!$B:$B,'Projects Cashflow'!$AG:$AG,0) -> 3296222 | AF135: =AE135-AB135 -> 0
B136: =D136&F136&H136&I136&J136 -> 45192034511001179Event Consumable-N2421125200104 | C136: Arabic Language Centre | D136: 4519203 | E136: ALC- Strategic Planning Office | F136: 4511001179 | G136: Arabian Days | H136: Event Consumable-N2 | I136: 421125 | J136: 200104 | K136: Opex | L136: 70704 | M136: Internal Strategic | N136: 0 | O136: 0 | P136: 0 | Q136: 0 | R136: 0 | S136: 0 | T136: 0 | U136: 0 | V136: 500000 | W136: 0 | X136: 0 | Y136: 0 | Z136: =SUM(N136:Y136) -> 500000 | AB136: 500000 | AC136: 500000 | AD136: 0 | AE136: =_xlfn.XLOOKUP(B136,'Projects Cashflow'!$B:$B,'Projects Cashflow'!$AG:$AG,0) -> 500000 | AF136: =AE136-AB136 -> 0
B137: =D137&F137&H137&I137&J137 -> 45192034511001179PR Mgmnt E-E-N2424781200104 | C137: Arabic Language Centre | D137: 4519203 | E137: ALC- Strategic Planning Office | F137: 4511001179 | G137: Arabian Days | H137: PR Mgmnt E-E-N2 | I137: 424781 | J137: 200104 | K137: Opex | L137: 70704 | M137: Internal Strategic | N137: 0 | O137: 0 | P137: 0 | Q137: 0 | R137: 0 | S137: 0 | T137: 0 | U137: 0 | V137: 0 | W137: 155288.33 | X137: 155288.33 | Y137: 155288.33 | Z137: =SUM(N137:Y137) -> 465865 | AB137: 465865 | AC137: 465865 | AD137: 0 | AE137: =_xlfn.XLOOKUP(B137,'Projects Cashflow'!$B:$B,'Projects Cashflow'!$AG:$AG,0) -> 465865 | AF137: =AE137-AB137 -> 0
B138: =D138&F138&H138&I138&J138 -> 45192034511001427Managed Service-N422212202067 | C138: Arabic Language Centre | D138: 4519203 | E138: ALC- Strategic Planning Office | F138: 4511001427 | G138: Digital Arabic Library | H138: Managed Service-N | I138: 422212 | J138: 202067 | K138: Opex | L138: 70705 | M138: Operational | N138: 0 | O138: 0 | P138: 5891624.8 | Q138: 8375.1651 | R138: 0 | S138: 0 | T138: 4720000 | U138: 0 | V138: 0 | W138: 0 | X138: 1180000 | Y138: 0 | Z138: =SUM(N138:Y138) -> 11800000 | AB138: 11800000 | AC138: 11800000 | AD138: 0 | AE138: =_xlfn.XLOOKUP(B138,'Projects Cashflow'!$B:$B,'Projects Cashflow'!$AG:$AG,0) -> 11800000 | AF138: =AE138-AB138 -> 0
B139: =D139&F139&H139&I139&J139 -> 45192034511001427Freelancers-N2424521202067 | C139: Arabic Language Centre | D139: 4519203 | E139: ALC- Strategic Planning Office | F139: 4511001427 | G139: Digital Arabic Library | H139: Freelancers-N2 | I139: 424521 | J139: 202067 | K139: Opex | L139: 70705 | M139: Internal Strategic | N139: 0 | O139: 0 | P139: 0 | Q139: 222222.22 | R139: 222222.22 | S139: 222222.22 | T139: 222222.22 | U139: 222222.22 | V139: 222222.22 | W139: 222222.22 | X139: 222222.22 | Y139: 222222.22 | Z139: =SUM(N139:Y139) -> 2000000 | AB139: 2000000 | AC139: 2000000 | AD139: 0 | AE139: =_xlfn.XLOOKUP(B139,'Projects Cashflow'!$B:$B,'Projects Cashflow'!$AG:$AG,0) -> 2000000 | AF139: =AE139-AB139 -> 0
B140: =D140&F140&H140&I140&J140 -> 45192034511001427Committee Member-N421115202067 | C140: Arabic Language Centre | D140: 4519203 | E140: ALC- Strategic Planning Office | F140: 4511001427 | G140: Digital Arabic Library | H140: Committee Member-N | I140: 421115 | J140: 202067 | K140: Opex | L140: 70705 | M140: Operational | N140: 0 | O140: 0 | P140: 0 | Q140: 0 | R140: 0 | S140: 0 | T140: 0 | U140: 0 | V140: 0 | W140: 0 | X140: 1000000 | Y140: 0 | Z140: =SUM(N140:Y140) -> 1000000 | AB140: 1000000 | AC140: 1000000 | AD140: 0 | AE140: =_xlfn.XLOOKUP(B140,'Projects Cashflow'!$B:$B,'Projects Cashflow'!$AG:$AG,0) -> 1000000 | AF140: =AE140-AB140 -> 0
B141: =D141&F141&H141&I141&J141 -> 45110104511000208Strategy Advice-N421123200104 | C141: Culture | D141: 4511010 | E141: DCT - Culture (Central) Dept | F141: 4511000208 | G141: CS - Executive Office | H141: Strategy Advice-N | I141: 421123 | J141: 200104 | K141: Opex | L141: 70303 | M141: Internal Strategic | N141: 0 | O141: 0 | P141: 0 | Q141: 0 | R141: 0 | S141: 0 | T141: 0 | U141: 0 | V141: 0 | W141: 4000000 | X141: 7321945 | Y141: 0 | Z141: =SUM(N141:Y141) -> 11321945 | AB141: 11321945 | AC141: 11321945 | AD141: 0 | AE141: =_xlfn.XLOOKUP(B141,'Projects Cashflow'!$B:$B,'Projects Cashflow'!$AG:$AG,0) -> 11321945 | AF141: =AE141-AB141 -> 0
B142: =D142&F142&H142&I142&J142 -> 45110104511000208Event Management-N422401200104 | C142: Culture | D142: 4511010 | E142: DCT - Culture (Central) Dept | F142: 4511000208 | G142: CS - Executive Office | H142: Event Management-N | I142: 422401 | J142: 200104 | K142: Opex | L142: 70303 | M142: Internal Strategic | N142: 0 | O142: 0 | P142: 154025.19 | Q142: 0 | R142: 0 | S142: 0 | T142: 1047033.4 | U142: 0 | V142: 751755.61 | W142: 280000 | X142: 3000000 | Y142: 5000000 | Z142: =SUM(N142:Y142) -> 10232814 | AB142: 4648813.2 | AC142: 4648813 | AD142: 0.19 | AE142: =_xlfn.XLOOKUP(B142,'Projects Cashflow'!$B:$B,'Projects Cashflow'!$AG:$AG,0) -> 4648813 | AF142: =AE142-AB142 -> -0.19
... B360: =D360&F360&H360&I360&J360 -> 45112504511000528Manpower-N424521200104 | C360: Culture | D360: 4511250 | E360: DCT - Culture Sites Management Department | F360: 4511000528 | G360: Jebel Hafit Desert Park | H360: Manpower-N | I360: 424521 | J360: 200104 | K360: Opex | L360: 70205 | M360: Internal Strategic | N360: 0 | O360: 0 | P360: 0 | Q360: 0 | R360: 15000 | S360: 15000 | T360: 15000 | U360: 15000 | V360: 15000 | W360: 15000 | X360: 15000 | Y360: 15000 | Z360: =SUM(N360:Y360) -> 120000 | AB360: 120000 | AC360: 120000 | AD360: 0 | AE360: =_xlfn.XLOOKUP(B360,'Projects Cashflow'!$B:$B,'Projects Cashflow'!$AG:$AG,0) -> 120000 | AF360: =AE360-AB360 -> 0
B361: =D361&F361&H361&I361&J361 -> 45112504511000580Activation&Prog-N422401200104 | C361: Culture | D361: 4511250 | E361: DCT - Culture Sites Management Department | F361: 4511000580 | G361: CF Main Exhibitions | H361: Activation&Prog-N | I361: 422401 | J361: 200104 | K361: Opex | L361: 70205 | M361: Internal Strategic | N361: 0 | O361: 534234 | P361: 0 | R361: 0 | S361: 927136 | T361: 0 | U361: 50000 | V361: 475000 | W361: 1314482 | X361: 432000 | Y361: 187726 | Z361: =SUM(N361:Y361) -> 3920578 | AB361: 3920578 | AC361: 3920578 | AD361: 0 | AE361: =_xlfn.XLOOKUP(B361,'Projects Cashflow'!$B:$B,'Projects Cashflow'!$AG:$AG,0) -> 3920578 | AF361: =AE361-AB361 -> 0
B362: =D362&F362&H362&I362&J362 -> 45112504511000580Freelancers-N424521200104 | C362: Culture | D362: 4511250 | E362: DCT - Culture Sites Management Department | F362: 4511000580 | G362: CF Main Exhibitions | H362: Freelancers-N | I362: 424521 | J362: 200104 | K362: Opex | L362: 70205 | M362: Internal Strategic | N362: 0 | O362: 0 | P362: 39000 | Q362: 117000 | R362: 39000 | S362: 39000 | T362: 39000 | U362: 39000 | V362: 0 | W362: 0 | X362: 0 | Y362: 0 | Z362: =SUM(N362:Y362) -> 312000 | AB362: 234000 | AC362: 234000 | AD362: 0 | AE362: =_xlfn.XLOOKUP(B362,'Projects Cashflow'!$B:$B,'Projects Cashflow'!$AG:$AG,0) -> 234000 | AF362: =AE362-AB362 -> 0
B363: =D363&F363&H363&I363&J363 -> 45112504511000580Manpower-N424521200104 | C363: Culture | D363: 4511250 | E363: DCT - Culture Sites Management Department | F363: 4511000580 | G363: CF Main Exhibitions | H363: Manpower-N | I363: 424521 | J363: 200104 | K363: Opex | L363: 70205 | M363: Internal Strategic | N363: 0 | O363: 0 | P363: 0 | Q363: 40000 | R363: 12000 | S363: 12000 | T363: 12000 | U363: 12000 | V363: 0 | W363: 0 | X363: 0 | Y363: 0 | Z363: =SUM(N363:Y363) -> 88000 | AB363: 166000 | AC363: 166000.05 | AD363: -0.05 | AE363: =_xlfn.XLOOKUP(B363,'Projects Cashflow'!$B:$B,'Projects Cashflow'!$AG:$AG,0) -> 166000.05 | AF363: =AE363-AB363 -> 0.05
B364: =D364&F364&H364&I364&J364 -> 45112504511000581Activation&Prog-N422401200104 | C364: Culture | D364: 4511250 | E364: DCT - Culture Sites Management Department | F364: 4511000581 | G364: CF Art Residenecy | H364: Activation&Prog-N | I364: 422401 | J364: 200104 | K364: Opex | L364: 70205 | M364: Internal Strategic | N364: 0 | O364: 0 | P364: 0 | Q364: 0 | R364: 0 | S364: 0 | T364: 0 | U364: 0 | V364: 0 | W364: 101500 | X364: 0 | Y364: 168500 | Z364: =SUM(N364:Y364) -> 270000 | AB364: 270000 | AC364: 270000 | AD364: 0 | AE364: =_xlfn.XLOOKUP(B364,'Projects Cashflow'!$B:$B,'Projects Cashflow'!$AG:$AG,0) -> 270000 | AF364: =AE364-AB364 -> 0
B365: =D365&F365&H365&I365&J365 -> 45112504511000581Freelancers-N424521200104 | C365: Culture | D365: 4511250 | E365: DCT - Culture Sites Management Department | F365: 4511000581 | G365: CF Art Residenecy | H365: Freelancers-N | I365: 424521 | J365: 200104 | K365: Opex | L365: 70205 | M365: Internal Strategic | N365: 0 | O365: 0 | P365: 39000 | Q365: 0 | R365: 23500 | S365: 0 | T365: 0 | U365: 62500 | V365: 0 | W365: 0 | X365: 0 | Y365: 125000 | Z365: =SUM(N365:Y365) -> 250000 | AB365: 250000 | AC365: 250000 | AD365: 0 | AE365: =_xlfn.XLOOKUP(B365,'Projects Cashflow'!$B:$B,'Projects Cashflow'!$AG:$AG,0) -> 250000 | AF365: =AE365-AB365 -> 0
B366: =D366&F366&H366&I366&J366 -> 45112504511000510Maintenance-N426212200104 | C366: Culture | D366: 4511250 | E366: DCT - Culture Sites Management Department | F366: 4511000510 | G366: Delma Museum | H366: Maintenance-N | I366: 426212 | J366: 200104 | K366: Opex | L366: 70205 | M366: Internal Strategic | N366: 0 | O366: 0 | P366: 0 | Q366: 31715 | R366: 7929 | S366: 7929 | T366: 7929 | U366: 7929 | V366: 7929 | W366: 7929 | X366: 7929 | Y366: 7924 | Z366: =SUM(N366:Y366) -> 95142 | AB366: 95142 | AC366: 95142 | AD366: 0 | AE366: =_xlfn.XLOOKUP(B366,'Projects Cashflow'!$B:$B,'Projects Cashflow'!$AG:$AG,0) -> 95142 | AF366: =AE366-AB366 -> 0
B367: =D367&F367&H367&I367&J367 -> 45112504511000583Manpower-N424521200104 | C367: Culture | D367: 4511250 | E367: DCT - Culture Sites Management Department | F367: 4511000583 | G367: CF Community Exhibitions | H367: Manpower-N | I367: 424521 | J367: 200104 | K367: Opex | L367: 70205 | M367: Internal Strategic | N367: 0 | O367: 0 | P367: 0 | Q367: 0 | R367: 0 | S367: 0 | T367: 9600 | U367: 80000 | V367: 25000 | W367: 10000 | X367: 15000 | Y367: 200000 | Z367: =SUM(N367:Y367) -> 339600 | AB367: 339600 | AC367: 339600 | AD367: 0 | AE367: =_xlfn.XLOOKUP(B367,'Projects Cashflow'!$B:$B,'Projects Cashflow'!$AG:$AG,0) -> 339600 | AF367: =AE367-AB367 -> 0
B368: =D368&F368&H368&I368&J368 -> 45112504511000623Facilities Rent-N425112200104 | C368: Culture | D368: 4511250 | E368: DCT - Culture Sites Management Department | F368: 4511000623 | G368: Bait Al Oud Site | H368: Facilities Rent-N | I368: 425112 | J368: 200104 | K368: Opex | L368: 70205 | M368: Internal Strategic | N368: 0 | O368: 0 | P368: 833490 | Q368: 0 | R368: 0 | S368: 0 | T368: 0 | U368: 0 | V368: 0 | W368: 0 | X368: 0 | Y368: 0 | Z368: =SUM(N368:Y368) -> 833490 | AB368: 833490 | AC368: 833490 | AD368: 0 | AE368: =_xlfn.XLOOKUP(B368,'Projects Cashflow'!$B:$B,'Projects Cashflow'!$AG:$AG,0) -> 833490 | AF368: =AE368-AB368 -> 0
B369: =D369&F369&H369&I369&J369 -> 45112504511000434Manpower-N424521200104 | C369: Culture | D369: 4511250 | E369: DCT - Culture Sites Management Department | F369: 4511000434 | G369: Berklee Abu Dhabi | H369: Manpower-N | I369: 424521 | J369: 200104 | K369: Opex | L369: 70205 | M369: Internal Strategic | N369: 0 | O369: 0 | P369: 51788.88 | Q369: 89683 | R369: 25894.44 | S369: 25894.44 | T369: 25894.44 | U369: 25894.44 | V369: 101683.32 | W369: 25894.44 | X369: 139956 | Y369: 71157 | Z369: =SUM(N369:Y369) -> 583740.4 | AB369: 583740.4 | AC369: 583740 | AD369: 0.4 | AE369: =_xlfn.XLOOKUP(B369,'Projects Cashflow'!$B:$B,'Projects Cashflow'!$AG:$AG,0) -> 583740 | AF369: =AE369-AB369 -> -0.4
B370: =D370&F370&H370&I370&J370 -> 45112504511000064Edu & Outreach-N422401200104 | C370: Culture | D370: 4511250 | E370: DCT - Culture Sites Management Department | F370: 4511000064 | G370: Qasr Al Muwaji | H370: Edu & Outreach-N | I370: 422401 | J370: 200104 | K370: Opex | L370: 70205 | M370: Internal Strategic | N370: 0 | O370: 0 | P370: 0 | Q370: 0 | R370: 0 | S370: 0 | T370: 0 | U370: 0 | V370: 0 | W370: 0 | X370: 0 | Y370: 135000 | Z370: =SUM(N370:Y370) -> 135000 | AB370: 135000 | AC370: 135000 | AD370: 0 | AE370: =_xlfn.XLOOKUP(B370,'Projects Cashflow'!$B:$B,'Projects Cashflow'!$AG:$AG,0) -> 135000 | AF370: =AE370-AB370 -> 0
B371: =D371&F371&H371&I371&J371 -> 45112504511000623Cleaning Service-N422311200104 | C371: Culture | D371: 4511250 | E371: DCT - Culture Sites Management Department | F371: 4511000623 | G371: Bait Al Oud Site | H371: Cleaning Service-N | I371: 422311 | J371: 200104 | K371: Opex | L371: 70205 | M371: Internal Strategic | N371: 0 | O371: 0 | P371: 0 | Q371: 30532 | R371: 7633 | S371: 7633 | T371: 7633 | U371: 7633 | V371: 7633 | W371: 7633 | X371: 7633 | Y371: 7613 | Z371: =SUM(N371:Y371) -> 91576 | AB371: 91576 | AC371: 91576.1 | AD371: -0.1 | AE371: =_xlfn.XLOOKUP(B371,'Projects Cashflow'!$B:$B,'Projects Cashflow'!$AG:$AG,0) -> 91576.1 | AF371: =AE371-AB371 -> 0.1
B372: =D372&F372&H372&I372&J372 -> 45112504511000283Landscaping-N432614200104 | C372: Culture | D372: 4511250 | E372: DCT - Culture Sites Management Department | F372: 4511000283 | G372: Qasr Al Hosn | H372: Landscaping-N | I372: 432614 | J372: 200104 | K372: Opex | L372: 70205 | M372: Internal Strategic | N372: 0 | O372: 0 | P372: 0 | Q372: 194444.68 | R372: 48611.17 | S372: 48611.17 | T372: 48611.17 | U372: 48611.17 | V372: 48611.16 | W372: 48611.16 | X372: 48611.16 | Y372: 48611.16 | Z372: =SUM(N372:Y372) -> 583334 | AB372: 583334 | AC372: 583334 | AD372: 0 | AE372: =_xlfn.XLOOKUP(B372,'Projects Cashflow'!$B:$B,'Projects Cashflow'!$AG:$AG,0) -> 583334 | AF372: =AE372-AB372 -> 0
B373: =D373&F373&H373&I373&J373 -> 45112504511000623Landscaping-N432614200104 | C373: Culture | D373: 4511250 | E373: DCT - Culture Sites Management Department | F373: 4511000623 | G373: Bait Al Oud Site | H373: Landscaping-N | I373: 432614 | J373: 200104 | K373: Opex | L373: 70205 | M373: Internal Strategic | N373: 0 | O373: 0 | P373: 0 | Q373: 3992 | R373: 998 | S373: 998 | T373: 998 | U373: 998 | V373: 998 | W373: 998 | X373: 998 | Y373: 998 | Z373: =SUM(N373:Y373) -> 11976 | AB373: 11976 | AC373: 11976.48 | AD373: -0.48 | AE373: =_xlfn.XLOOKUP(B373,'Projects Cashflow'!$B:$B,'Projects Cashflow'!$AG:$AG,0) -> 11976.48 | AF373: =AE373-AB373 -> 0.48
... B442: =D442&F442&H442&I442&J442 -> 45113004511000227Plant & Tools-N491351300105 | C442: Culture | D442: 4511300 | E442: DCT - Historical Environment Dept | F442: 4511000227 | G442: Tangible Heritage Operations. | H442: Plant & Tools-N | I442: 491351 | J442: 300105 | K442: Capex | L442: 70201 | M442: Internal Strategic | N442: 0 | O442: 0 | P442: 7700 | Q442: 0 | R442: 0 | S442: 108833.54 | T442: 9558.04 | U442: 326670 | V442: 667238 | W442: 630000 | X442: 550000 | Y442: 700000 | Z442: =SUM(N442:Y442) -> 2999999.6 | AB442: 8999999.6 | AC442: 9000000 | AD442: -0.42 | AE442: =_xlfn.XLOOKUP(B442,'Projects Cashflow'!$B:$B,'Projects Cashflow'!$AG:$AG,0) -> 9000000 | AF442: =AE442-AB442 -> 0.42
B443: =D443&F443&H443&I443&J443 -> 45113004511000227Admin Expenses-N421125200104 | C443: Culture | D443: 4511300 | E443: DCT - Historical Environment Dept | F443: 4511000227 | G443: Tangible Heritage Operations. | H443: Admin Expenses-N | I443: 421125 | J443: 200104 | K443: Opex | L443: 70201 | M443: Internal Strategic | N443: 0 | O443: 71939.5 | P443: 75777.51 | R443: 100029 | S443: 50000 | T443: 200000 | U443: 200000 | V443: 200000 | W443: 300000 | X443: 400000 | Y443: 502254 | Z443: =SUM(N443:Y443) -> 2100000 | AB443: 1748354 | AC443: 1748354 | AD443: 0.0099999998 | AE443: =_xlfn.XLOOKUP(B443,'Projects Cashflow'!$B:$B,'Projects Cashflow'!$AG:$AG,0) -> 1748354 | AF443: =AE443-AB443 -> -0.0099999998
B444: =D444&F444&H444&I444&J444 -> 45113004511000227Mission & Travel-N423821200104 | C444: Culture | D444: 4511300 | E444: DCT - Historical Environment Dept | F444: 4511000227 | G444: Tangible Heritage Operations. | H444: Mission & Travel-N | I444: 423821 | J444: 200104 | K444: Opex | L444: 70201 | M444: Internal Strategic | N444: 0 | O444: 73850 | P444: 36600 | Q444: 29800 | R444: 144750 | S444: 0 | T444: 200000 | U444: 100000 | V444: 100000 | W444: 100000 | X444: 100000 | Y444: 411049 | Z444: =SUM(N444:Y444) -> 1296049 | AB444: 1296049 | AC444: 1296049 | AD444: 0 | AE444: =_xlfn.XLOOKUP(B444,'Projects Cashflow'!$B:$B,'Projects Cashflow'!$AG:$AG,0) -> 1296049 | AF444: =AE444-AB444 -> 0
B445: =D445&F445&H445&I445&J445 -> 45113004511000637Freelancers-N424521200104 | C445: Culture | D445: 4511300 | E445: DCT - Historical Environment Dept | F445: 4511000637 | G445: Archaeology | H445: Freelancers-N | I445: 424521 | J445: 200104 | K445: Opex | L445: 70201 | M445: Internal Strategic | N445: 0 | O445: 0 | P445: 1488593.4 | Q445: 0 | R445: 0 | S445: 185506.26 | T445: 515572.84 | U445: 412569.84 | V445: 1055631 | W445: 2878421 | X445: 1172410 | Y445: 1181761.6 | Z445: =SUM(N445:Y445) -> 8890466 | AB445: 7890466 | AC445: 7890466 | AD445: 0 | AE445: =_xlfn.XLOOKUP(B445,'Projects Cashflow'!$B:$B,'Projects Cashflow'!$AG:$AG,0) -> 7890466 | AF445: =AE445-AB445 -> 0
B446: =D446&F446&H446&I446&J446 -> 45113004511000637Event Management-N422401200104 | C446: Culture | D446: 4511300 | E446: DCT - Historical Environment Dept | F446: 4511000637 | G446: Archaeology | H446: Event Management-N | I446: 422401 | J446: 200104 | K446: Opex | L446: 70201 | M446: Internal Strategic | N446: 0 | O446: 0 | P446: 0 | Q446: 42000 | R446: 0 | S446: 0 | T446: 0 | U446: 0 | V446: 0 | W446: 0 | X446: 0 | Y446: 0 | Z446: =SUM(N446:Y446) -> 42000 | AB446: 42000 | AC446: 42000 | AD446: 0 | AE446: =_xlfn.XLOOKUP(B446,'Projects Cashflow'!$B:$B,'Projects Cashflow'!$AG:$AG,0) -> 42000 | AF446: =AE446-AB446 -> 0
B447: =D447&F447&H447&I447&J447 -> 45113004511000639Event Management-N422401200104 | C447: Culture | D447: 4511300 | E447: DCT - Historical Environment Dept | F447: 4511000639 | G447: Conservation | H447: Event Management-N | I447: 422401 | J447: 200104 | K447: Opex | L447: 70201 | M447: Internal Strategic | N447: 0 | O447: 0 | P447: 0 | Q447: 0 | R447: 0 | S447: 0 | T447: 1245684 | U447: 400000 | V447: 4772921 | W447: 581395 | X447: 0 | Y447: 0 | Z447: =SUM(N447:Y447) -> 7000000 | AB447: 4555000 | AC447: 4555000 | AD447: 0 | AE447: =_xlfn.XLOOKUP(B447,'Projects Cashflow'!$B:$B,'Projects Cashflow'!$AG:$AG,0) -> 4555000 | AF447: =AE447-AB447 -> 0
B448: =D448&F448&H448&I448&J448 -> 45113004511000639Research&Survey-N423411200104 | C448: Culture | D448: 4511300 | E448: DCT - Historical Environment Dept | F448: 4511000639 | G448: Conservation | H448: Research&Survey-N | I448: 423411 | J448: 200104 | K448: Opex | L448: 70201 | M448: Internal Strategic | N448: 0 | O448: 0 | P448: 0 | Q448: 120412 | R448: 259515 | S448: 410000 | T448: 530000 | U448: 0 | V448: 1220000 | W448: 90000 | X448: 860000 | Y448: 1321996 | Z448: =SUM(N448:Y448) -> 4811923 | AB448: 5181396 | AC448: 5181396 | AD448: 0 | AE448: =_xlfn.XLOOKUP(B448,'Projects Cashflow'!$B:$B,'Projects Cashflow'!$AG:$AG,0) -> 5181396 | AF448: =AE448-AB448 -> 0
B449: =D449&F449&H449&I449&J449 -> 45113004511000639Freelancers-N424521200104 | C449: Culture | D449: 4511300 | E449: DCT - Historical Environment Dept | F449: 4511000639 | G449: Conservation | H449: Freelancers-N | I449: 424521 | J449: 200104 | K449: Opex | L449: 70201 | M449: Internal Strategic | N449: 0 | O449: 279017.5 | P449: 124625.5 | Q449: 0 | R449: 0 | S449: 31701 | T449: 80418 | U449: 74268 | V449: 74268 | W449: 139268 | X449: 99268 | Y449: 104719 | Z449: =SUM(N449:Y449) -> 1007553 | AB449: 1267553 | AC449: 1267553 | AD449: 0 | AE449: =_xlfn.XLOOKUP(B449,'Projects Cashflow'!$B:$B,'Projects Cashflow'!$AG:$AG,0) -> 1267553 | AF449: =AE449-AB449 -> 0
B450: =D450&F450&H450&I450&J450 -> 45113004511000639Conserv-Restore-N3421125200104 | C450: Culture | D450: 4511300 | E450: DCT - Historical Environment Dept | F450: 4511000639 | G450: Conservation | H450: Conserv-Restore-N3 | I450: 421125 | J450: 200104 | K450: Opex | L450: 70201 | M450: Internal Strategic | N450: 0 | O450: 0 | P450: 0 | Q450: 0 | R450: 149500 | S450: 50000 | T450: 3000 | U450: 143000 | V450: 148000 | W450: 52175 | X450: 35000 | Y450: 231488 | Z450: =SUM(N450:Y450) -> 812163 | AB450: 1133458 | AC450: 1133458 | AD450: 0 | AE450: =_xlfn.XLOOKUP(B450,'Projects Cashflow'!$B:$B,'Projects Cashflow'!$AG:$AG,0) -> 1133458 | AF450: =AE450-AB450 -> 0
B451: =D451&F451&H451&I451&J451 -> 45113004511000639Cultural Advice-N424521200104 | C451: Culture | D451: 4511300 | E451: DCT - Historical Environment Dept | F451: 4511000639 | G451: Conservation | H451: Cultural Advice-N | I451: 424521 | J451: 200104 | K451: Opex | L451: 70201 | M451: Internal Strategic | N451: 0 | O451: 0 | P451: 0 | Q451: 0 | R451: 0 | S451: 391500 | T451: 0 | U451: 0 | V451: 0 | W451: 0 | X451: 193500 | Y451: 0 | Z451: =SUM(N451:Y451) -> 585000 | AB451: 991000 | AC451: 991000 | AD451: 0 | AE451: =_xlfn.XLOOKUP(B451,'Projects Cashflow'!$B:$B,'Projects Cashflow'!$AG:$AG,0) -> 991000 | AF451: =AE451-AB451 -> 0
B452: =D452&F452&H452&I452&J452 -> 45113004511000639Architect Advice-N424521200104 | C452: Culture | D452: 4511300 | E452: DCT - Historical Environment Dept | F452: 4511000639 | G452: Conservation | H452: Architect Advice-N | I452: 424521 | J452: 200104 | K452: Opex | L452: 70201 | M452: Internal Strategic | N452: 0 | O452: 0 | P452: 0 | Q452: 0 | R452: 0 | S452: 0 | T452: 125000 | U452: 25000 | V452: 25000 | W452: 25000 | X452: 15000 | Y452: 0 | Z452: =SUM(N452:Y452) -> 215000 | AB452: 1430000 | AC452: 1430000 | AD452: 0 | AE452: =_xlfn.XLOOKUP(B452,'Projects Cashflow'!$B:$B,'Projects Cashflow'!$AG:$AG,0) -> 1430000 | AF452: =AE452-AB452 -> 0
B453: =D453&F453&H453&I453&J453 -> 45113004511000641CollectionConsrv-N421191200104 | C453: Culture | D453: 4511300 | E453: DCT - Historical Environment Dept | F453: 4511000641 | G453: Historic Buildings & Landscapes | H453: CollectionConsrv-N | I453: 421191 | J453: 200104 | K453: Opex | L453: 70201 | M453: Internal Strategic | N453: 0 | O453: 0 | P453: 0 | Q453: 0 | R453: 300000 | S453: 300000 | T453: 0 | U453: 400000 | V453: 400000 | W453: 0 | X453: 250000 | Y453: 0 | Z453: =SUM(N453:Y453) -> 1650000 | AB453: 1333821 | AC453: 1333821 | AD453: 0 | AE453: =_xlfn.XLOOKUP(B453,'Projects Cashflow'!$B:$B,'Projects Cashflow'!$AG:$AG,0) -> 1333821 | AF453: =AE453-AB453 -> 0
B454: =D454&F454&H454&I454&J454 -> 45113004511000641Freelancers-N424521200104 | C454: Culture | D454: 4511300 | E454: DCT - Historical Environment Dept | F454: 4511000641 | G454: Historic Buildings & Landscapes | H454: Freelancers-N | I454: 424521 | J454: 200104 | K454: Opex | L454: 70201 | M454: Internal Strategic | N454: 0 | O454: 0 | P454: 93000 | Q454: 0 | R454: 0 | S454: 0 | T454: 0 | U454: 50000 | V454: 0 | W454: 557000 | X454: 0 | Y454: 0 | Z454: =SUM(N454:Y454) -> 700000 | AB454: 522000 | AC454: 522000 | AD454: 0 | AE454: =_xlfn.XLOOKUP(B454,'Projects Cashflow'!$B:$B,'Projects Cashflow'!$AG:$AG,0) -> 522000 | AF454: =AE454-AB454 -> 0
B455: =D455&F455&H455&I455&J455 -> 45113004511000644FeasibilityStudy-N424521200104 | C455: Culture | D455: 4511300 | E455: DCT - Historical Environment Dept | F455: 4511000644 | G455: Modern Heritage | H455: FeasibilityStudy-N | I455: 424521 | J455: 200104 | K455: Opex | L455: 70201 | M455: Internal Strategic | N455: 0 | O455: 0 | P455: 0 | Q455: 0 | R455: 0 | S455: 627488 | T455: 250000 | U455: 800000 | V455: 627488 | W455: 250000 | X455: 663884 | Y455: 0 | Z455: =SUM(N455:Y455) -> 3218860 | AB455: 3758860 | AC455: 3758860 | AD455: 0 | AE455: =_xlfn.XLOOKUP(B455,'Projects Cashflow'!$B:$B,'Projects Cashflow'!$AG:$AG,0) -> 3758860 | AF455: =AE455-AB455 -> 0
... B463: =D463&F463&H463&I463&J463 -> 45113004511001544Research&Survey-N423411200104 | C463: Culture | D463: 4511300 | E463: DCT - Historical Environment Dept | F463: 4511001544 | G463: Archaeology - Terrestrial | H463: Research&Survey-N | I463: 423411 | J463: 200104 | K463: Opex | L463: 70204 | M463: Internal Strategic | N463: 0 | O463: 0 | P463: 0 | Q463: 0 | R463: 0 | S463: 70000 | T463: 105235 | U463: 190000 | V463: 172500 | W463: 317000 | X463: 1165000 | Y463: 0 | Z463: =SUM(N463:Y463) -> 2019735 | AB463: 2019735 | AC463: 2019735 | AD463: 0 | AE463: =_xlfn.XLOOKUP(B463,'Projects Cashflow'!$B:$B,'Projects Cashflow'!$AG:$AG,0) -> 2019735 | AF463: =AE463-AB463 -> 0
B464: =D464&F464&H464&I464&J464 -> 45115504511000019PR Mgmnt E-E-N424781200104 | C464: Culture | D464: 4511550 | E464: DCT - Culture Sector Marketing Department | F464: 4511000019 | G464: Al Qattara Art Centre | H464: PR Mgmnt E-E-N | I464: 424781 | J464: 200104 | K464: Opex | L464: 70206 | M464: Internal Strategic | Z464: =SUM(N464:Y464) -> 0 | AB464: 4750 | AC464: 4750 | AD464: 0 | AE464: =_xlfn.XLOOKUP(B464,'Projects Cashflow'!$B:$B,'Projects Cashflow'!$AG:$AG,0) -> 0 | AF464: =AE464-AB464 -> -4750
...
